Workbook

Sheet Raw_Data
A1: show_id | B1: type | C1: title | D1: director | E1: cast | F1: country | G1: date_added | H1: release_year | I1: rating | J1: duration | K1: listed_in | L1: description | M1: year_added | N1: IncludeRow
A2: s5 | B2: TV Show | C2: Kota Factory | E2: Mayur More, Jitendra Kumar, Ranjan Raj, Alam Khan, Ahsaas Channa, Revathi Pillai, Urvi Singh, Arun Kumar | F2: India | G2: 2021-09-24 | H2: 2021 | I2: TV-MA | J2: 2 Seasons | K2: International TV Shows, Romantic TV Shows, TV Comedies | L2: In a city of coaching centers known to train India’s finest collegiate minds, an earnest but unexceptional student and his friends navigate campus life. | M2: 2021 | N2: =IF(AND(OR(YearFilter="All",$M2=YearFilter),OR(RatingFilter="All",$I2=RatingFilter),OR(TypeFilter="All",$B2=TypeFilter),OR(GenreFilter="All",COUNTIFS(tblGenre[show_id],$A2,tblGenre[Genre],GenreFilter)>0)),1,0)
A3: s25 | B3: Movie | C3: Jeans | D3: S. Shankar | E3: Prashanth, Aishwarya Rai Bachchan, Sri Lakshmi, Nassar | F3: India | G3: 2021-09-21 | H3: 1998 | I3: TV-14 | J3: 166 min | K3: Comedies, International Movies, Romantic Movies | L3: When the father of the man she loves insists that his twin sons marry twin sisters, a woman creates an alter ego that might be a bit too convincing. | M3: 2021 | N3: =IF(AND(OR(YearFilter="All",$M3=YearFilter),OR(RatingFilter="All",$I3=RatingFilter),OR(TypeFilter="All",$B3=TypeFilter),OR(GenreFilter="All",COUNTIFS(tblGenre[show_id],$A3,tblGenre[Genre],GenreFilter)>0)),1,0)
A4: s30 | B4: Movie | C4: Paranoia | D4: Robert Luketic | E4: Liam Hemsworth, Gary Oldman, Amber Heard, Harrison Ford, Lucas Till, Embeth Davidtz, Julian McMahon, Josh Holloway, Richard Dreyfuss, Angela Sarafyan | F4: United States, India, France | G4: 2021-09-19 | H4: 2013 | I4: PG-13 | J4: 106 min | K4: Thrillers | L4: Blackmailed by his company's CEO, a low-level employee finds himself forced to spy on the boss's rival and former mentor. | M4: 2021 | N4: =IF(AND(OR(YearFilter="All",$M4=YearFilter),OR(RatingFilter="All",$I4=RatingFilter),OR(TypeFilter="All",$B4=TypeFilter),OR(GenreFilter="All",COUNTIFS(tblGenre[show_id],$A4,tblGenre[Genre],GenreFilter)>0)),1,0)
A5: s40 | B5: TV Show | C5: Chhota Bheem | E5: Vatsal Dubey, Julie Tejwani, Rupa Bhimani, Jigna Bhardwaj, Rajesh Kava, Mousam, Swapnil | F5: India | G5: 2021-09-16 | H5: 2021 | I5: TV-Y7 | J5: 3 Seasons | K5: Kids' TV | L5: A brave, energetic little boy with superhuman powers leads his friends on exciting adventures to guard their fellow Dholakpur villagers from evil. | M5: 2021 | N5: =IF(AND(OR(YearFilter="All",$M5=YearFilter),OR(RatingFilter="All",$I5=RatingFilter),OR(TypeFilter="All",$B5=TypeFilter),OR(GenreFilter="All",COUNTIFS(tblGenre[show_id],$A5,tblGenre[Genre],GenreFilter)>0)),1,0)
A6: s51 | B6: TV Show | C6: Dharmakshetra | E6: Kashmira Irani, Chandan Anand, Dinesh Mehta, Ankit Arora, Pushkar Goggiaa, Anjali Rana, Aarya DharmChand Kumar, Amit Behl, Maleeka Ghai | F6: India | G6: 2021-09-15 | H6: 2014 | I6: TV-PG | J6: 1 Season | K6: International TV Shows, TV Dramas, TV Sci-Fi & Fantasy | L6: After the ancient Great War, the god Chitragupta oversees a trial to determine who were the battle's true heroes and villains. | M6: 2021 | N6: =IF(AND(OR(YearFilter="All",$M6=YearFilter),OR(RatingFilter="All",$I6=RatingFilter),OR(TypeFilter="All",$B6=TypeFilter),OR(GenreFilter="All",COUNTIFS(tblGenre[show_id],$A6,tblGenre[Genre],GenreFilter)>0)),1,0)
A7: s67 | B7: TV Show | C7: Raja Rasoi Aur Anya Kahaniyan | F7: India | G7: 2021-09-15 | H7: 2014 | I7: TV-G | J7: 1 Season | K7: Docuseries, International TV Shows | L7: Explore the history and flavors of regional Indian cuisine, from traditional Kashmiri feasts to the vegetarian dishes of Gujarat. | M7: 2021 | N7: =IF(AND(OR(YearFilter="All",$M7=YearFilter),OR(RatingFilter="All",$I7=RatingFilter),OR(TypeFilter="All",$B7=TypeFilter),OR(GenreFilter="All",COUNTIFS(tblGenre[show_id],$A7,tblGenre[Genre],GenreFilter)>0)),1,0)
A8: s70 | B8: TV Show | C8: Stories by Rabindranath Tagore | F8: India | G8: 2021-09-15 | H8: 2015 | I8: TV-PG | J8: 1 Season | K8: International TV Shows, TV Dramas | L8: The writings of Nobel Prize winner Rabindranath Tagore come to life in this collection of tales set in early-20th-century Bengal. | M8: 2021 | N8: =IF(AND(OR(YearFilter="All",$M8=YearFilter),OR(RatingFilter="All",$I8=RatingFilter),OR(TypeFilter="All",$B8=TypeFilter),OR(GenreFilter="All",COUNTIFS(tblGenre[show_id],$A8,tblGenre[Genre],GenreFilter)>0)),1,0)
A9: s106 | B9: Movie | C9: Angamaly Diaries | D9: Lijo Jose Pellissery | E9: Antony Varghese, Reshma Rajan, Binny Rinky Benjamin, Vineeth Vishwam, Kichu Tellus, Sreekanth Dasan, Sarath Kumar, Tito Wilson, Anandhu, Bitto Davis, Sinoj Varghese | F9: India | G9: 2021-09-05 | H9: 2017 | I9: TV-14 | J9: 128 min | K9: Action & Adventure, Comedies, Dramas | L9: After growing up amidst the gang wars of his hometown, Vincent forms an entrepreneurial squad of his own and ends up on the wrong side of the law. | M9: 2021 | N9: =IF(AND(OR(YearFilter="All",$M9=YearFilter),OR(RatingFilter="All",$I9=RatingFilter),OR(TypeFilter="All",$B9=TypeFilter),OR(GenreFilter="All",COUNTIFS(tblGenre[show_id],$A9,tblGenre[Genre],GenreFilter)>0)),1,0)
A10: s115 | B10: Movie | C10: Anjaam | D10: Rahul Rawail | E10: Madhuri Dixit, Shah Rukh Khan, Tinnu Anand, Johny Lever, Kalpana Iyer, Himani Shivpuri, Sudha Chandran, Beena, Kiran Kumar | F10: India | G10: 2021-09-02 | H10: 1994 | I10: TV-14 | J10: 143 min | K10: Dramas, International Movies, Thrillers | L10: A wealthy industrialist’s dangerous obsession with a flight attendant destroys her world, until she takes matters into her own hands to exact revenge. | M10: 2021 | N10: =IF(AND(OR(YearFilter="All",$M10=YearFilter),OR(RatingFilter="All",$I10=RatingFilter),OR(TypeFilter="All",$B10=TypeFilter),OR(GenreFilter="All",COUNTIFS(tblGenre[show_id],$A10,tblGenre[Genre],GenreFilter)>0)),1,0)
A11: s117 | B11: Movie | C11: Dhanak | D11: Nagesh Kukunoor | E11: Krrish Chhabria, Hetal Gada, Vipin Sharma, Gulfam Khan, Suresh Menon, Vijay Maurya, Rajiv Lakshman, Ninad Kamat | F11: India | G11: 2021-09-02 | H11: 2015 | I11: TV-PG | J11: 114 min | K11: Comedies, Dramas, Independent Movies | L11: A movie-loving 10-year-old and her blind little brother trek to meet Indian superstar Shah Rukh Khan for help in getting the boy an eye operation. | M11: 2021 | N11: =IF(AND(OR(YearFilter="All",$M11=YearFilter),OR(RatingFilter="All",$I11=RatingFilter),OR(TypeFilter="All",$B11=TypeFilter),OR(GenreFilter="All",COUNTIFS(tblGenre[show_id],$A11,tblGenre[Genre],GenreFilter)>0)),1,0)
A12: s119 | B12: Movie | C12: Gurgaon | D12: Shanker Raman | E12: Akshay Oberoi, Pankaj Tripathi, Ragini Khanna, Aamir Bashir, Shalini Vatsa, Ashish Verma | F12: India | G12: 2021-09-02 | H12: 2017 | I12: TV-14 | J12: 106 min | K12: Dramas, International Movies, Thrillers | L12: When the daughter of a wealthy family returns from college, she gets a frosty welcome from her brother, who has problems – and plans – of his own. | M12: 2021 | N12: =IF(AND(OR(YearFilter="All",$M12=YearFilter),OR(RatingFilter="All",$I12=RatingFilter),OR(TypeFilter="All",$B12=TypeFilter),OR(GenreFilter="All",COUNTIFS(tblGenre[show_id],$A12,tblGenre[Genre],GenreFilter)>0)),1,0)
A13: s127 | B13: Movie | C13: Shikara | D13: Vidhu Vinod Chopra | E13: Aadil Khan, Sadia Khateeb, Zain Khan Durrani, Priyanshu Chatterjee, Bhavna Chauhan, Ashwin Dhar, Farid Azad Khan, Saghar Sehrai | F13: India | G13: 2021-09-02 | H13: 2020 | I13: TV-14 | J13: 115 min | K13: Dramas, International Movies, Romantic Movies | L13: A couple must strive to remain resilient after regional hostilities drive them from their beloved home into a refugee camp. | M13: 2021 | N13: =IF(AND(OR(YearFilter="All",$M13=YearFilter),OR(RatingFilter="All",$I13=RatingFilter),OR(TypeFilter="All",$B13=TypeFilter),OR(GenreFilter="All",COUNTIFS(tblGenre[show_id],$A13,tblGenre[Genre],GenreFilter)>0)),1,0)
A14: s191 | B14: Movie | C14: Thimmarusu | D14: Sharan Koppisetty | E14: Satya Dev, Priyanka Jawalkar, Brahmaji | F14: India | G14: 2021-08-28 | H14: 2021 | I14: TV-14 | J14: 125 min | K14: Dramas, International Movies | L14: Eight years after a young man is framed for murder, an up-and-coming lawyer re-opens the case, beginning a tricky mission to find the real culprit. | M14: 2021 | N14: =IF(AND(OR(YearFilter="All",$M14=YearFilter),OR(RatingFilter="All",$I14=RatingFilter),OR(TypeFilter="All",$B14=TypeFilter),OR(GenreFilter="All",COUNTIFS(tblGenre[show_id],$A14,tblGenre[Genre],GenreFilter)>0)),1,0)
A15: s193 | B15: Movie | C15: C Kkompany | D15: Sachin Yardi | E15: Mithun Chakraborty, Tusshar Kapoor, Anupam Kher, Rajpal Yadav, Raima Sen, Dilip Prabhavalkar, Sanjay Mishra | F15: India | G15: 2021-08-27 | H15: 2008 | I15: TV-14 | J15: 127 min | K15: Action & Adventure, Comedies, International Movies | L15: Three broke friends pose as an underworld gang for extortion, but their plan takes on a life of its own when their phony company becomes famous. | M15: 2021 | N15: =IF(AND(OR(YearFilter="All",$M15=YearFilter),OR(RatingFilter="All",$I15=RatingFilter),OR(TypeFilter="All",$B15=TypeFilter),OR(GenreFilter="All",COUNTIFS(tblGenre[show_id],$A15,tblGenre[Genre],GenreFilter)>0)),1,0)
A16: s196 | B16: Movie | C16: EMI: Liya Hai To Chukana Padega | D16: Saurabh Kabra | E16: Sanjay Dutt, Arjun Rampal, Malaika Arora, Aashish Chaudhary, Neha Uberoi, Urmila Matondkar, Manoj Joshi, Daya Shankar Pandey, Pushkar Jog, Kulbhushan Kharbanda | F16: India | G16: 2021-08-27 | H16: 2008 | I16: TV-14 | J16: 128 min | K16: Comedies, Dramas, International Movies | L16: A bank hires an enigmatic and unorthodox debt collector to recover money from four borrowers who are unable to pay their loans. | M16: 2021 | N16: =IF(AND(OR(YearFilter="All",$M16=YearFilter),OR(RatingFilter="All",$I16=RatingFilter),OR(TypeFilter="All",$B16=TypeFilter),OR(GenreFilter="All",COUNTIFS(tblGenre[show_id],$A16,tblGenre[Genre],GenreFilter)>0)),1,0)
A17: s200 | B17: Movie | C17: Koi Aap Sa | D17: Partho Mitra | E17: Aftab Shivdasani, Natassha, Dipannita Sharma, Himanshu Mallik, Vaidya Advai, Pushy Anand, Shama Deshpande, Rajendra Gupta | F17: India | G17: 2021-08-27 | H17: 2006 | I17: TV-14 | J17: 135 min | K17: Comedies, Dramas, International Movies | L17: Star athlete Rohan has his eye on a beautiful art student. But when his best friend Simran experiences a crisis, he drops everything to help her. | M17: 2021 | N17: =IF(AND(OR(YearFilter="All",$M17=YearFilter),OR(RatingFilter="All",$I17=RatingFilter),OR(TypeFilter="All",$B17=TypeFilter),OR(GenreFilter="All",COUNTIFS(tblGenre[show_id],$A17,tblGenre[Genre],GenreFilter)>0)),1,0)
A18: s201 | B18: Movie | C18: Krishna Cottage | D18: Santram Varma | E18: Sohail Khan, Isha Koppikar, Natassha, Rati Agnihotri, Vrajesh Hirjee, Divya Palat, Hiten Tejwani, Rajendranath Zutshi | F18: India | G18: 2021-08-27 | H18: 2004 | I18: TV-14 | J18: 124 min | K18: Action & Adventure, Horror Movies, International Movies | L18: True love is put to the test when another woman comes between a pair of star-crossed young lovers in this thriller. | M18: 2021 | N18: =IF(AND(OR(YearFilter="All",$M18=YearFilter),OR(RatingFilter="All",$I18=RatingFilter),OR(TypeFilter="All",$B18=TypeFilter),OR(GenreFilter="All",COUNTIFS(tblGenre[show_id],$A18,tblGenre[Genre],GenreFilter)>0)),1,0)
A19: s202 | B19: Movie | C19: Kucch To Hai | D19: Anil V. Kumar, Anurag Basu | E19: Tusshar Kapoor, Esha Deol, Natassha, Vrajesh Hirjee, Kusumit Sana, Rishi Kapoor, Moon Moon Sen, Johny Lever, Ashay Chitre, Jeetendra | F19: India | G19: 2021-08-27 | H19: 2003 | I19: TV-14 | J19: 136 min | K19: Dramas, International Movies, Thrillers | L19: A student tries to steal a test from a teacher's home, leaving him for dead after an accident. A string of murders may be the professor's revenge. | M19: 2021 | N19: =IF(AND(OR(YearFilter="All",$M19=YearFilter),OR(RatingFilter="All",$I19=RatingFilter),OR(TypeFilter="All",$B19=TypeFilter),OR(GenreFilter="All",COUNTIFS(tblGenre[show_id],$A19,tblGenre[Genre],GenreFilter)>0)),1,0)
A20: s203 | B20: Movie | C20: Kyaa Kool Hai Hum | D20: Sangeeth Sivan | E20: Tusshar Kapoor, Riteish Deshmukh, Isha Koppikar, Neha Dhupia, Anupam Kher, Jay Sean | F20: India | G20: 2021-08-27 | H20: 2005 | I20: TV-MA | J20: 165 min | K20: Comedies, International Movies, Music & Musicals | L20: Longtime friends Rahul and Karan head to Mumbai intent on making their dreams come true, but both men are suddenly saddled with bad luck. | M20: 2021 | N20: =IF(AND(OR(YearFilter="All",$M20=YearFilter),OR(RatingFilter="All",$I20=RatingFilter),OR(TypeFilter="All",$B20=TypeFilter),OR(GenreFilter="All",COUNTIFS(tblGenre[show_id],$A20,tblGenre[Genre],GenreFilter)>0)),1,0)
... A34: s260 | B34: Movie | C34: Pahuna | D34: Paakhi Tyrewala | E34: Anmol Limbu, Ishika Gurung, Manju Chettri, Banita Lagun, Binod Pradhan, Mahindra Bajgai, Rupa Tamang, Saran Rai | F34: India, Nepal | G34: 2021-08-18 | H34: 2018 | I34: TV-PG | J34: 82 min | K34: Comedies, Dramas, International Movies | L34: Fleeing unrest in their native Nepal, three young siblings separated from their parents must beat the odds to survive on their own in India. | M34: 2021 | N34: =IF(AND(OR(YearFilter="All",$M34=YearFilter),OR(RatingFilter="All",$I34=RatingFilter),OR(TypeFilter="All",$B34=TypeFilter),OR(GenreFilter="All",COUNTIFS(tblGenre[show_id],$A34,tblGenre[Genre],GenreFilter)>0)),1,0)
A35: s267 | B35: TV Show | C35: The Creative Indians | F35: India | G35: 2021-08-15 | H35: 2020 | I35: TV-MA | J35: 1 Season | K35: Docuseries, International TV Shows | L35: From chefs and comedians to filmmakers and fashion designers, India’s most notable imaginative minds share their artistic journeys. | M35: 2021 | N35: =IF(AND(OR(YearFilter="All",$M35=YearFilter),OR(RatingFilter="All",$I35=RatingFilter),OR(TypeFilter="All",$B35=TypeFilter),OR(GenreFilter="All",COUNTIFS(tblGenre[show_id],$A35,tblGenre[Genre],GenreFilter)>0)),1,0)
A36: s298 | B36: TV Show | C36: Navarasa | D36: Bejoy Nambiar, Priyadarshan, Karthik Narain, Vasanth Sai, Karthik Subbaraj, Arvind Swamy, Rathindran R Prasad, Sarjun, Gautham Vasudev Menon | E36: Suriya, Vijay Sethupathi, Revathy, Prakash Raj, Siddarth, Parvathy, Delhi Ganesh, Gautham Vasudev Menon, Anjali, Yogi Babu, Aditi Balan, Remya Nambeesan, Poorna, Prayaga Martin, Rythvika Suriya, Arvind Swamy, Prasanna, Atharva, Bobby Simha, Ashok Selvan, Nedumudi Venu, Kishore | F36: India | G36: 2021-08-06 | H36: 2021 | I36: TV-MA | J36: 1 Season | K36: TV Shows | L36: From amusement to awe, the nine human emotions of Indian aesthetic theory are explored in this anthology series. | M36: 2021 | N36: =IF(AND(OR(YearFilter="All",$M36=YearFilter),OR(RatingFilter="All",$I36=RatingFilter),OR(TypeFilter="All",$B36=TypeFilter),OR(GenreFilter="All",COUNTIFS(tblGenre[show_id],$A36,tblGenre[Genre],GenreFilter)>0)),1,0)
A37: s302 | B37: Movie | C37: Chennai Express | D37: Rohit Shetty | E37: Shah Rukh Khan, Deepika Padukone, Nikitin Dheer, Satyaraj, Kamini Kaushal, Lekh Tandon, Mukesh Tiwari | F37: India | G37: 2021-08-05 | H37: 2013 | I37: TV-14 | J37: 135 min | K37: Action & Adventure, Comedies, International Movies | L37: What could have been a sad journey turns joyful for Rahul when he falls in love with a woman en route to submerging his grandfather's ashes. | M37: 2021 | N37: =IF(AND(OR(YearFilter="All",$M37=YearFilter),OR(RatingFilter="All",$I37=RatingFilter),OR(TypeFilter="All",$B37=TypeFilter),OR(GenreFilter="All",COUNTIFS(tblGenre[show_id],$A37,tblGenre[Genre],GenreFilter)>0)),1,0)
A38: s384 | B38: Movie | C38: Department | D38: Ram Gopal Varma | E38: Amitabh Bachchan, Sanjay Dutt, Rana Daggubati, Vijay Raaz, Abhimanyu Singh, Madhu Shalini, Deepak Tijori, Anjana Sukhani, Manchu Lakshmi | F38: India | G38: 2021-07-27 | H38: 2012 | I38: TV-MA | J38: 143 min | K38: Action & Adventure, International Movies | L38: Two cops form a task force to take down two mobsters, but when a sinister politician enters the picture, dubious loyalties and motives come to light. | M38: 2021 | N38: =IF(AND(OR(YearFilter="All",$M38=YearFilter),OR(RatingFilter="All",$I38=RatingFilter),OR(TypeFilter="All",$B38=TypeFilter),OR(GenreFilter="All",COUNTIFS(tblGenre[show_id],$A38,tblGenre[Genre],GenreFilter)>0)),1,0)
A39: s411 | B39: Movie | C39: Chhota Bheem And The Broken Amulet | D39: Rajiv Chilaka | E39: Vatsal Dubey, Julie Tejwani, Rupa Bhimani, Jigna Bhardwaj, Rajesh Kava, Mousam, Swapnil | F39: India | G39: 2021-07-22 | H39: 2013 | I39: TV-Y7 | J39: 64 min | K39: Children & Family Movies | L39: When a stranger tries to steal an amulet from the palace, Bheem learns the sad story behind the ornament and heads to Africa to defeat the real villain. | M39: 2021 | N39: =IF(AND(OR(YearFilter="All",$M39=YearFilter),OR(RatingFilter="All",$I39=RatingFilter),OR(TypeFilter="All",$B39=TypeFilter),OR(GenreFilter="All",COUNTIFS(tblGenre[show_id],$A39,tblGenre[Genre],GenreFilter)>0)),1,0)
A40: s416 | B40: Movie | C40: Chhota Bheem aur Krishna | D40: Rajiv Chilaka | E40: Vatsal Dubey, Julie Tejwani, Rupa Bhimani, Jigna Bhardwaj, Rajesh Kava, Arun Shekher, Sanchit Wartak | F40: India | G40: 2021-07-22 | H40: 2009 | I40: TV-Y7 | J40: 68 min | K40: Children & Family Movies | L40: Centuries after the end of a conqueror's rule, he is mysteriously back from the dead. It’s up to Bheem to save Dholakpur from being taken over! | M40: 2021 | N40: =IF(AND(OR(YearFilter="All",$M40=YearFilter),OR(RatingFilter="All",$I40=RatingFilter),OR(TypeFilter="All",$B40=TypeFilter),OR(GenreFilter="All",COUNTIFS(tblGenre[show_id],$A40,tblGenre[Genre],GenreFilter)>0)),1,0)
A41: s519 | B41: Movie | C41: Har Kisse Ke Hisse: Kaamyaab | D41: Hardik Mehta | E41: Sanjay Mishra, Deepak Dobriyal, Sarika Singh, Isha Talwar, Avtar Gill, Kaurwakee Vashistha, Amitabh Srivastava, Vikas Verma | F41: India | G41: 2021-07-06 | H41: 2020 | I41: TV-14 | J41: 105 min | K41: Dramas, International Movies | L41: After a career of thankless credits, a retired actor returns for a long-awaited leading role but finds he is utterly unprepared for new-age filmmaking. | M41: 2021 | N41: =IF(AND(OR(YearFilter="All",$M41=YearFilter),OR(RatingFilter="All",$I41=RatingFilter),OR(TypeFilter="All",$B41=TypeFilter),OR(GenreFilter="All",COUNTIFS(tblGenre[show_id],$A41,tblGenre[Genre],GenreFilter)>0)),1,0)
A42: s529 | B42: Movie | C42: Rehmataan | D42: Rajveer Singh Maan, Harpeet Singh | E42: Guggu Gill, Sukhjinder Shera, Surinder Shinda, Deep Dhillon, Jasmine Jassi, Gurvinder Brar, Razia Sukhvir, Raj Virk | F42: India | G42: 2021-07-06 | H42: 2012 | I42: TV-14 | J42: 116 min | K42: Dramas, International Movies, Romantic Movies | L42: As unemployment, drug addiction and corruption plague a society, this drama depicts the people who believe there’s still good in the world. | M42: 2021 | N42: =IF(AND(OR(YearFilter="All",$M42=YearFilter),OR(RatingFilter="All",$I42=RatingFilter),OR(TypeFilter="All",$B42=TypeFilter),OR(GenreFilter="All",COUNTIFS(tblGenre[show_id],$A42,tblGenre[Genre],GenreFilter)>0)),1,0)
A43: s542 | B43: Movie | C43: Truckbhar Swapna | D43: Pramod Pawar | E43: Makrand Deshpande, Kranti Redkar, Mukesh Rishi, Manoj Joshi, Smita Tambe, Aaditi Pohankar, Sahil Gilbile, Jyoti Joshi | F43: India | G43: 2021-07-06 | H43: 2018 | I43: TV-14 | J43: 128 min | K43: Comedies, Dramas, International Movies | L43: A taxi driver living in a Mumbai slum seeks to better his family's life by building an extension of his home while dealing with a lecherous contractor. | M43: 2021 | N43: =IF(AND(OR(YearFilter="All",$M43=YearFilter),OR(RatingFilter="All",$I43=RatingFilter),OR(TypeFilter="All",$B43=TypeFilter),OR(GenreFilter="All",COUNTIFS(tblGenre[show_id],$A43,tblGenre[Genre],GenreFilter)>0)),1,0)
A44: s543 | B44: Movie | C44: Ujala | D44: Naresh Saigal | E44: Mala Sinha, Shammi Kapoor, Raaj Kumar, Leela Chitnis, Dhumal, Kumkum | F44: India | G44: 2021-07-06 | H44: 1959 | I44: TV-14 | J44: 143 min | K44: Dramas, International Movies | L44: An honest man dreams of a better life for his family, but a childhood friend leads him into a world of crime that keeps happiness just out of reach. | M44: 2021 | N44: =IF(AND(OR(YearFilter="All",$M44=YearFilter),OR(RatingFilter="All",$I44=RatingFilter),OR(TypeFilter="All",$B44=TypeFilter),OR(GenreFilter="All",COUNTIFS(tblGenre[show_id],$A44,tblGenre[Genre],GenreFilter)>0)),1,0)
A45: s552 | B45: Movie | C45: Haseen Dillruba | D45: Vinil Mathew | E45: Taapsee Pannu, Vikrant Massey, Harshvardhan Rane, Aditya Srivastava, Ashish Verma, Yamini Das, Daya Shankar Pandey | F45: India | G45: 2021-07-02 | H45: 2021 | I45: TV-MA | J45: 136 min | K45: International Movies, Romantic Movies, Thrillers | L45: Under investigation as a suspect in her husband’s murder, a wife reveals details of their thorny marriage that seem to only further blur the truth. | M45: 2021 | N45: =IF(AND(OR(YearFilter="All",$M45=YearFilter),OR(RatingFilter="All",$I45=RatingFilter),OR(TypeFilter="All",$B45=TypeFilter),OR(GenreFilter="All",COUNTIFS(tblGenre[show_id],$A45,tblGenre[Genre],GenreFilter)>0)),1,0)
A46: s736 | B46: Movie | C46: Sarbath | D46: Prabhakaran | E46: Kathir, Soori, Rahasya Gorak, Ashvatt | F46: India | G46: 2021-06-11 | H46: 2021 | I46: TV-PG | J46: 113 min | K46: Comedies, Dramas, International Movies | L46: When a city man returns to his native village for his brother’s wedding, several unforeseen snags make his visit more eventful than anticipated. | M46: 2021 | N46: =IF(AND(OR(YearFilter="All",$M46=YearFilter),OR(RatingFilter="All",$I46=RatingFilter),OR(TypeFilter="All",$B46=TypeFilter),OR(GenreFilter="All",COUNTIFS(tblGenre[show_id],$A46,tblGenre[Genre],GenreFilter)>0)),1,0)
A47: s737 | B47: Movie | C47: Skater Girl | D47: Manjari Makijany | E47: Rachel Saanchita Gupta, Amy Maghera, Shafin Patel, Ambrish Saxena, Swati Das, Jonathan Readwin, Ankit Yadav, Anurag Arora, Vinayak Gupta, Vivek Yadav, Waheeda Rehman | F47: United States, India | G47: 2021-06-11 | H47: 2021 | I47: PG | J47: 110 min | K47: Children & Family Movies, Dramas, International Movies | L47: When a teen in rural India discovers a life-changing passion for skateboarding, she faces a rough road as she follows her dream to compete. | M47: 2021 | N47: =IF(AND(OR(YearFilter="All",$M47=YearFilter),OR(RatingFilter="All",$I47=RatingFilter),OR(TypeFilter="All",$B47=TypeFilter),OR(GenreFilter="All",COUNTIFS(tblGenre[show_id],$A47,tblGenre[Genre],GenreFilter)>0)),1,0)
... A50: s874 | B50: Movie | C50: Ahaan | D50: Nikhil Pherwani | E50: Arif Zakaria, Abuli Mamaji, Niharika Singh, Rajit Kapoor, Plabita Borthakur, Shilpa Mehta, Kaizaad Kotwal, Sonali Sachdev, Haresh Raut | F50: India | G50: 2021-05-15 | H50: 2021 | I50: TV-MA | J50: 81 min | K50: Dramas, Independent Movies, International Movies | L50: Jilted by his wife, a man with OCD finds eye-opening common ground and camaraderie with his neighbor, a young man with Down Syndrome. | M50: 2021 | N50: =IF(AND(OR(YearFilter="All",$M50=YearFilter),OR(RatingFilter="All",$I50=RatingFilter),OR(TypeFilter="All",$B50=TypeFilter),OR(GenreFilter="All",COUNTIFS(tblGenre[show_id],$A50,tblGenre[Genre],GenreFilter)>0)),1,0)
A51: s877 | B51: TV Show | C51: Alma Matters | F51: India | G51: 2021-05-14 | H51: 2021 | I51: TV-MA | J51: 1 Season | K51: Docuseries, International TV Shows | L51: Alumni of India’s elite academic institutes share the harsh realities, pleasant surprises and transformative journeys of their college experiences. | M51: 2021 | N51: =IF(AND(OR(YearFilter="All",$M51=YearFilter),OR(RatingFilter="All",$I51=RatingFilter),OR(TypeFilter="All",$B51=TypeFilter),OR(GenreFilter="All",COUNTIFS(tblGenre[show_id],$A51,tblGenre[Genre],GenreFilter)>0)),1,0)
A52: s878 | B52: Movie | C52: Cinema Bandi | D52: Praveen Kandregula | E52: Vikas Vasistha, Sandeep Varanasi, Rag Mayur, Trishara, Munivenkatapa, Uma Yg, Sirivennela Yanamandhala, Sindhu Sreenivasa Murthy | F52: India | G52: 2021-05-14 | H52: 2021 | I52: TV-MA | J52: 99 min | K52: Comedies, Independent Movies, International Movies | L52: A struggling rickshaw driver’s life takes a rollicking turn when he comes upon an expensive camera and decides to make a film with his fellow villagers. | M52: 2021 | N52: =IF(AND(OR(YearFilter="All",$M52=YearFilter),OR(RatingFilter="All",$I52=RatingFilter),OR(TypeFilter="All",$B52=TypeFilter),OR(GenreFilter="All",COUNTIFS(tblGenre[show_id],$A52,tblGenre[Genre],GenreFilter)>0)),1,0)
A53: s893 | B53: Movie | C53: Tottaa Pataaka Item Maal | D53: Aditya Kripalani | E53: Shalini Vatsa, Chitrangada Chakraborty, Vinay Sharma, Sonal Joshi, Kritika Pande | F53: India | G53: 2021-05-13 | H53: 2018 | I53: TV-MA | J53: 107 min | K53: Dramas, Independent Movies, International Movies | L53: Exasperated with living in perpetual fear for their safety, four women kidnap a man to show him the realities of being female in Delhi. | M53: 2021 | N53: =IF(AND(OR(YearFilter="All",$M53=YearFilter),OR(RatingFilter="All",$I53=RatingFilter),OR(TypeFilter="All",$B53=TypeFilter),OR(GenreFilter="All",COUNTIFS(tblGenre[show_id],$A53,tblGenre[Genre],GenreFilter)>0)),1,0)
A54: s904 | B54: Movie | C54: Nayattu | D54: Martin Prakkat | E54: Kunchacko Boban, Joju George, Nimisha Sajayan, Jaffer Idukki, Yama Gilgamesh, Anil Nedumangad, Dineesh P, Vinod Sagar | F54: India | G54: 2021-05-09 | H54: 2021 | I54: TV-MA | J54: 122 min | K54: Dramas, International Movies, Thrillers | L54: Three police officers become pawns for unscrupulous lawmakers when they are framed in an incident amid political elections and must flee to evade arrest. | M54: 2021 | N54: =IF(AND(OR(YearFilter="All",$M54=YearFilter),OR(RatingFilter="All",$I54=RatingFilter),OR(TypeFilter="All",$B54=TypeFilter),OR(GenreFilter="All",COUNTIFS(tblGenre[show_id],$A54,tblGenre[Genre],GenreFilter)>0)),1,0)
A55: s910 | B55: Movie | C55: Milestone | D55: Ivan Ayr | E55: Suvinder Vicky, Lakshvir Saran, Mohinder Gujral, Gurinder Makna, Daljeet Singh, Akhilesh Kumar, Gaurika Bhatt, Arun Aseng | F55: India | G55: 2021-05-07 | H55: 2021 | I55: TV-14 | J55: 98 min | K55: Dramas, Independent Movies, International Movies | L55: Recently marking 500,000 kilometers on the road, a newly bereaved trucker faces the threat of losing the job that has come to define him to a new intern. | M55: 2021 | N55: =IF(AND(OR(YearFilter="All",$M55=YearFilter),OR(RatingFilter="All",$I55=RatingFilter),OR(TypeFilter="All",$B55=TypeFilter),OR(GenreFilter="All",COUNTIFS(tblGenre[show_id],$A55,tblGenre[Genre],GenreFilter)>0)),1,0)
A56: s912 | B56: TV Show | C56: Sab Jholmaal Hai | D56: Vijay Roche | F56: India | G56: 2021-05-07 | H56: 2017 | I56: TV-Y7 | J56: 2 Seasons | K56: Kids' TV, TV Comedies | L56: In this madcap comedy, two mischievous cats, a talking parrot and a high-strung dog keep getting into trouble while their human is away. | M56: 2021 | N56: =IF(AND(OR(YearFilter="All",$M56=YearFilter),OR(RatingFilter="All",$I56=RatingFilter),OR(TypeFilter="All",$B56=TypeFilter),OR(GenreFilter="All",COUNTIFS(tblGenre[show_id],$A56,tblGenre[Genre],GenreFilter)>0)),1,0)
A57: s914 | B57: Movie | C57: Time to Dance | D57: Stanley Menino D'Costa | E57: Sooraj Pancholi, Isabelle Kaif, Rajpal Yadav, Waluscha D'Souza, Natasha Powell, Martin Rycroft, Amrit Maghera, Saqib Saleem | F57: India | G57: 2021-05-07 | H57: 2020 | I57: TV-PG | J57: 107 min | K57: Dramas, International Movies, Romantic Movies | L57: When a ballroom dancer’s shot at a crucial tournament is jeopardized, a street dancer must face his own painful past and step up as her new partner. | M57: 2021 | N57: =IF(AND(OR(YearFilter="All",$M57=YearFilter),OR(RatingFilter="All",$I57=RatingFilter),OR(TypeFilter="All",$B57=TypeFilter),OR(GenreFilter="All",COUNTIFS(tblGenre[show_id],$A57,tblGenre[Genre],GenreFilter)>0)),1,0)
A58: s919 | B58: TV Show | C58: Lava Ka Dhaava | E58: Jaaved Jaaferi, Rutledge Wood | F58: India | G58: 2021-05-05 | H58: 2021 | I58: TV-PG | J58: 1 Season | K58: Reality TV | L58: Actor Jaaved Jaafferi brings his signature humor to this Hindi dubbing of the show where teams creatively navigate rooms flooded with make-believe lava. | M58: 2021 | N58: =IF(AND(OR(YearFilter="All",$M58=YearFilter),OR(RatingFilter="All",$I58=RatingFilter),OR(TypeFilter="All",$B58=TypeFilter),OR(GenreFilter="All",COUNTIFS(tblGenre[show_id],$A58,tblGenre[Genre],GenreFilter)>0)),1,0)
A59: s960 | B59: Movie | C59: The Disciple | D59: Chaitanya Tamhane | E59: Aditya Modak, Arun Dravid, Sumitra Bhave, Deepika Bhide Bhagwat, Kiran Yadnyopavit, Abhishek Kale, Neela Khedkar, Makarand Mukund, Kristy Banerjee, Prasad Vanarse | F59: India | G59: 2021-04-30 | H59: 2021 | I59: TV-MA | J59: 128 min | K59: Dramas, Independent Movies, International Movies | L59: Self-doubt, sacrifice and struggle converge into an existential crisis for a devoted classical vocalist as the mastery he strives for remains elusive. | M59: 2021 | N59: =IF(AND(OR(YearFilter="All",$M59=YearFilter),OR(RatingFilter="All",$I59=RatingFilter),OR(TypeFilter="All",$B59=TypeFilter),OR(GenreFilter="All",COUNTIFS(tblGenre[show_id],$A59,tblGenre[Genre],GenreFilter)>0)),1,0)
A60: s974 | B60: Movie | C60: One | D60: Santhosh Viswanath | E60: Mammootty, Joju George, Murali Gopy, Mathew Thomas, Nimisha Sajayan, Salim Kumar, Gayathri Arun, Ishaani Krishna | F60: India | G60: 2021-04-27 | H60: 2020 | I60: TV-PG | J60: 149 min | K60: Dramas, International Movies | L60: A formidable Kerala chief minister’s party loyalties and personal principles are tested when a damning social media post sparks a heated power struggle. | M60: 2021 | N60: =IF(AND(OR(YearFilter="All",$M60=YearFilter),OR(RatingFilter="All",$I60=RatingFilter),OR(TypeFilter="All",$B60=TypeFilter),OR(GenreFilter="All",COUNTIFS(tblGenre[show_id],$A60,tblGenre[Genre],GenreFilter)>0)),1,0)
A61: s975 | B61: Movie | C61: Ram Prasad Ki Tehrvi | D61: Seema Pahwa | E61: Supriya Pathak, Parambrata Chatterjee, Konkona Sen Sharma, Vikrant Massey, Manoj Pahwa, Vinay Pathak, Ninad Kamat, Naseeruddin Shah | F61: India | G61: 2021-04-24 | H61: 2019 | I61: TV-14 | J61: 113 min | K61: Dramas, Independent Movies, International Movies | L61: Conflicts, complications and confrontations make for an emotional and eventful affair when a multigenerational family reunites in Lucknow. | M61: 2021 | N61: =IF(AND(OR(YearFilter="All",$M61=YearFilter),OR(RatingFilter="All",$I61=RatingFilter),OR(TypeFilter="All",$B61=TypeFilter),OR(GenreFilter="All",COUNTIFS(tblGenre[show_id],$A61,tblGenre[Genre],GenreFilter)>0)),1,0)
A62: s999 | B62: Movie | C62: Searching For Sheela | E62: Ma Anand Sheela | F62: India | G62: 2021-04-22 | H62: 2021 | I62: TV-14 | J62: 58 min | K62: Documentaries, International Movies | L62: Journalists and fans await Ma Anand Sheela as the infamous former Rajneesh commune’s spokesperson returns to India after decades for an interview tour. | M62: 2021 | N62: =IF(AND(OR(YearFilter="All",$M62=YearFilter),OR(RatingFilter="All",$I62=RatingFilter),OR(TypeFilter="All",$B62=TypeFilter),OR(GenreFilter="All",COUNTIFS(tblGenre[show_id],$A62,tblGenre[Genre],GenreFilter)>0)),1,0)
A63: s1017 | B63: Movie | C63: Delhi Belly | D63: Abhinay Deo | E63: Imran Khan, Vir Das, Kunaal Roy Kapur, Poorna Jagannathan, Shenaz Treasury, Vijay Raaz, Paresh Ganatra, Rahul Singh | F63: India | G63: 2021-04-17 | H63: 2011 | I63: TV-MA | J63: 101 min | K63: Action & Adventure, Comedies, International Movies | L63: Three flatmates get involved in the shady business belonging to one roomie's fiancé, and discover that a global crime syndicate is gunning for them. | M63: 2021 | N63: =IF(AND(OR(YearFilter="All",$M63=YearFilter),OR(RatingFilter="All",$I63=RatingFilter),OR(TypeFilter="All",$B63=TypeFilter),OR(GenreFilter="All",COUNTIFS(tblGenre[show_id],$A63,tblGenre[Genre],GenreFilter)>0)),1,0)
A64: s1018 | B64: Movie | C64: Dhobi Ghat (Mumbai Diaries) | D64: Kiran Rao | E64: Aamir Khan, Monica Dogra, Kriti Malhotra, Prateik Babbar, Aasha Pawar, Jyoti Pawar, Norma Lobo, Kitu Gidwani, Danish Husain, Jehan Manekshaw | F64: India | G64: 2021-04-17 | H64: 2010 | I64: TV-MA | J64: 102 min | K64: Dramas, International Movies | L64: In this intimate drama, circumstances draw together four people from different castes – which would normally preclude them from forming friendships. | M64: 2021 | N64: =IF(AND(OR(YearFilter="All",$M64=YearFilter),OR(RatingFilter="All",$I64=RatingFilter),OR(TypeFilter="All",$B64=TypeFilter),OR(GenreFilter="All",COUNTIFS(tblGenre[show_id],$A64,tblGenre[Genre],GenreFilter)>0)),1,0)
A65: s1019 | B65: Movie | C65: Jaane Tu... Ya Jaane Na | D65: Abbas Tyrewala | E65: Imran Khan, Genelia D'Souza, Manjari Fadnis, Ayaz Khan, Prateik Babbar, Ratna Pathak Shah, Arbaaz Khan, Sohail Khan | F65: India | G65: 2021-04-17 | H65: 2008 | I65: TV-14 | J65: 147 min | K65: Comedies, International Movies, Music & Musicals | L65: Soft-spoken Jai and spitfire beauty Aditi couldn't be more different – but their family and friends know that they're a perfect match. | M65: 2021 | N65: =IF(AND(OR(YearFilter="All",$M65=YearFilter),OR(RatingFilter="All",$I65=RatingFilter),OR(TypeFilter="All",$B65=TypeFilter),OR(GenreFilter="All",COUNTIFS(tblGenre[show_id],$A65,tblGenre[Genre],GenreFilter)>0)),1,0)
A66: s1020 | B66: Movie | C66: Lagaan | D66: Ashutosh Gowariker | E66: Aamir Khan, Gracy Singh, Rachel Shelley, Paul Blackthorne, Kulbhushan Kharbanda, Raghuvir Yadav, Yashpal Sharma, Rajendranath Zutshi, Rajesh Vivek, Aditya Lakhia | F66: India, United Kingdom | G66: 2021-04-17 | H66: 2001 | I66: PG | J66: 224 min | K66: Dramas, International Movies, Music & Musicals | L66: In 1890s India, an arrogant British commander challenges the harshly taxed residents of Champaner to a high-stakes cricket match. | M66: 2021 | N66: =IF(AND(OR(YearFilter="All",$M66=YearFilter),OR(RatingFilter="All",$I66=RatingFilter),OR(TypeFilter="All",$B66=TypeFilter),OR(GenreFilter="All",COUNTIFS(tblGenre[show_id],$A66,tblGenre[Genre],GenreFilter)>0)),1,0)
A67: s1021 | B67: Movie | C67: Madness in the Desert | D67: Satyajit Bhatkal | E67: Aamir Khan, Ashutosh Gowariker | F67: India | G67: 2021-04-17 | H67: 2004 | I67: TV-14 | J67: 141 min | K67: Documentaries, International Movies | L67: The story of making "Lagaan," one of the millennium's seminal Indian films, is told from the point of view of production team member Satyajit Bhatkal. | M67: 2021 | N67: =IF(AND(OR(YearFilter="All",$M67=YearFilter),OR(RatingFilter="All",$I67=RatingFilter),OR(TypeFilter="All",$B67=TypeFilter),OR(GenreFilter="All",COUNTIFS(tblGenre[show_id],$A67,tblGenre[Genre],GenreFilter)>0)),1,0)
A68: s1022 | B68: Movie | C68: Peepli Live | D68: Anusha Rizvi, Mahmood Farooqui | E68: Omkar Das Manikpuri, Raghuvir Yadav, Malaika Shenoy, Nawazuddin Siddiqui, Naseeruddin Shah, Sitaram Panchal, Shalini Vatsa, Farrukh Jaffar, Aamir Bashir, Vishal Om Prakash | F68: India | G68: 2021-04-17 | H68: 2010 | I68: TV-MA | J68: 109 min | K68: Comedies, Dramas, Independent Movies | L68: Two indigent farmers consider suicide so that their families can collect a government subsidy that's paid to the relatives of deceased farmers. | M68: 2021 | N68: =IF(AND(OR(YearFilter="All",$M68=YearFilter),OR(RatingFilter="All",$I68=RatingFilter),OR(TypeFilter="All",$B68=TypeFilter),OR(GenreFilter="All",COUNTIFS(tblGenre[show_id],$A68,tblGenre[Genre],GenreFilter)>0)),1,0)
A69: s1023 | B69: Movie | C69: Taare Zameen Par | D69: Aamir Khan | E69: Aamir Khan, Darsheel Safary, Tanay Chheda, Tisca Chopra, Vipin Sharma, Girija Oak, M.K. Raina | F69: India | G69: 2021-04-17 | H69: 2007 | I69: PG | J69: 162 min | K69: Dramas, International Movies | L69: When daydreamer Ishaan is sent to boarding school, an unconventional art teacher tries to help the imaginative student discover his true identity. | M69: 2021 | N69: =IF(AND(OR(YearFilter="All",$M69=YearFilter),OR(RatingFilter="All",$I69=RatingFilter),OR(TypeFilter="All",$B69=TypeFilter),OR(GenreFilter="All",COUNTIFS(tblGenre[show_id],$A69,tblGenre[Genre],GenreFilter)>0)),1,0)
A70: s1024 | B70: Movie | C70: Ajeeb Daastaans | D70: Shashank Khaitan, Raj Mehta, Neeraj Ghaywan, Kayoze Irani | E70: Fatima Sana Shaikh, Jaideep Ahlawat, Armaan Ralhan, Nushrat Bharucha, Abhishek Banerjee, Inayat Verma, Konkona Sen Sharma, Aditi Rao Hydari, Shefali Shah, Manav Kaul, Tota Roy Chowdhury | F70: India | G70: 2021-04-16 | H70: 2021 | I70: TV-MA | J70: 142 min | K70: Dramas, Independent Movies, International Movies | L70: Four shorts explore the surprising ways in which unexpected catalysts inflame the uncomfortable emotions simmering under fractured relationships. | M70: 2021 | N70: =IF(AND(OR(YearFilter="All",$M70=YearFilter),OR(RatingFilter="All",$I70=RatingFilter),OR(TypeFilter="All",$B70=TypeFilter),OR(GenreFilter="All",COUNTIFS(tblGenre[show_id],$A70,tblGenre[Genre],GenreFilter)>0)),1,0)
A71: s1038 | B71: Movie | C71: Tuesdays & Fridays | D71: Taranveer Singh | E71: Anmol Thakeria Dhillon, Jhataleka, Niki Walia, Kamini Khanna, Zoa Morani, Nayan Shukla, Eklavyey Kashyap, Reem Shaikh | F71: India | G71: 2021-04-16 | H71: 2021 | I71: TV-14 | J71: 106 min | K71: Comedies, Dramas, International Movies | L71: To avoid the burden of commitment, a young lawyer and a writer agree to be romantic partners only two days a week. That won’t get complicated — right? | M71: 2021 | N71: =IF(AND(OR(YearFilter="All",$M71=YearFilter),OR(RatingFilter="All",$I71=RatingFilter),OR(TypeFilter="All",$B71=TypeFilter),OR(GenreFilter="All",COUNTIFS(tblGenre[show_id],$A71,tblGenre[Genre],GenreFilter)>0)),1,0)
A72: s1061 | B72: TV Show | C72: Indian Matchmaking | F72: United States, India | G72: 2021-04-14 | H72: 2020 | I72: TV-14 | J72: 1 Season | K72: Reality TV, Romantic TV Shows | L72: Matchmaker Sima Taparia guides clients in the U.S. and India in the arranged marriage process, offering an inside look at the custom in a modern era. | M72: 2021 | N72: =IF(AND(OR(YearFilter="All",$M72=YearFilter),OR(RatingFilter="All",$I72=RatingFilter),OR(TypeFilter="All",$B72=TypeFilter),OR(GenreFilter="All",COUNTIFS(tblGenre[show_id],$A72,tblGenre[Genre],GenreFilter)>0)),1,0)
A73: s1070 | B73: Movie | C73: Uppena | D73: Buchi Babu Sana | E73: Panja Vaisshnav Tej, Krithi Shetty, Vijay Sethupathi | F73: India | G73: 2021-04-14 | H73: 2020 | I73: TV-14 | J73: 145 min | K73: Dramas, International Movies, Romantic Movies | L73: The son of a fishing community falls for a village head's daughter, but they face violent opposition from the girl’s doggedly old-fashioned father. | M73: 2021 | N73: =IF(AND(OR(YearFilter="All",$M73=YearFilter),OR(RatingFilter="All",$I73=RatingFilter),OR(TypeFilter="All",$B73=TypeFilter),OR(GenreFilter="All",COUNTIFS(tblGenre[show_id],$A73,tblGenre[Genre],GenreFilter)>0)),1,0)
A74: s1076 | B74: TV Show | C74: My Love: Six Stories of True Love | D74: Moyoung Jin, Caroline Sá, Deepti Kakkar, Fahad Mustafa, Hikaru Toda, Chico Pereira, Elaine McMillion Sheldon | F74: United States, Brazil, Japan, Spain, India | G74: 2021-04-13 | H74: 2021 | I74: TV-PG | J74: 1 Season | K74: Docuseries | L74: Six longtime couples in different parts of the world share their decades-long love in these tender portraits filmed over the course of one year. | M74: 2021 | N74: =IF(AND(OR(YearFilter="All",$M74=YearFilter),OR(RatingFilter="All",$I74=RatingFilter),OR(TypeFilter="All",$B74=TypeFilter),OR(GenreFilter="All",COUNTIFS(tblGenre[show_id],$A74,tblGenre[Genre],GenreFilter)>0)),1,0)
A75: s1088 | B75: Movie | C75: Roohi | D75: Hardik Mehta | E75: Rajkummar Rao, Varun Sharma, Janhvi Kapoor, Manav Vij, Sarita Joshi, Anuraag Arora, Alexx O'Nell, Rajesh Jais | F75: India | G75: 2021-04-09 | H75: 2021 | I75: TV-14 | J75: 133 min | K75: Comedies, Horror Movies, International Movies | L75: Hired to kidnap a bride, two bumbling pals face a wacky predicament when one falls for their abductee — and the other, for the spirit possessing her. | M75: 2021 | N75: =IF(AND(OR(YearFilter="All",$M75=YearFilter),OR(RatingFilter="All",$I75=RatingFilter),OR(TypeFilter="All",$B75=TypeFilter),OR(GenreFilter="All",COUNTIFS(tblGenre[show_id],$A75,tblGenre[Genre],GenreFilter)>0)),1,0)
A76: s1094 | B76: TV Show | C76: The Big Day | F76: India | G76: 2021-04-07 | H76: 2021 | I76: TV-14 | J76: 2 Seasons | K76: International TV Shows, Reality TV, Romantic TV Shows | L76: For six engaged couples, happily ever after begins on a spectacular note in this eye-popping look at India’s multibillion-dollar wedding industry. | M76: 2021 | N76: =IF(AND(OR(YearFilter="All",$M76=YearFilter),OR(RatingFilter="All",$I76=RatingFilter),OR(TypeFilter="All",$B76=TypeFilter),OR(GenreFilter="All",COUNTIFS(tblGenre[show_id],$A76,tblGenre[Genre],GenreFilter)>0)),1,0)
A77: s1099 | B77: Movie | C77: Mandela | D77: Madonne Ashwin | E77: Yogi Babu, Sheela Rajkumar, Sangili Murugan, G. M. Sundhar | F77: India | G77: 2021-04-05 | H77: 2021 | I77: TV-14 | J77: 140 min | K77: Comedies, Dramas, International Movies | L77: Amid a local election with two rivals vying to win by any means necessary, a barber lands in a curiously powerful position as the single deciding vote. | M77: 2021 | N77: =IF(AND(OR(YearFilter="All",$M77=YearFilter),OR(RatingFilter="All",$I77=RatingFilter),OR(TypeFilter="All",$B77=TypeFilter),OR(GenreFilter="All",COUNTIFS(tblGenre[show_id],$A77,tblGenre[Genre],GenreFilter)>0)),1,0)
A78: s1109 | B78: Movie | C78: Irul | D78: Naseef Yusuf Izuddin | E78: Fahadh Faasil, Soubin Shahir, Darshana Rajendran | F78: India | G78: 2021-04-02 | H78: 2021 | I78: TV-MA | J78: 91 min | K78: International Movies, Thrillers | L78: When a car breakdown forces a couple to seek shelter in a nearby home, conversations with the stranger inside soon suggest there’s a killer among them. | M78: 2021 | N78: =IF(AND(OR(YearFilter="All",$M78=YearFilter),OR(RatingFilter="All",$I78=RatingFilter),OR(TypeFilter="All",$B78=TypeFilter),OR(GenreFilter="All",COUNTIFS(tblGenre[show_id],$A78,tblGenre[Genre],GenreFilter)>0)),1,0)
A79: s1115 | B79: Movie | C79: 3 Idiots | D79: Rajkumar Hirani | E79: Aamir Khan, Kareena Kapoor, Madhavan, Sharman Joshi, Omi Vaidya, Boman Irani, Mona Singh, Javed Jaffrey | F79: India | G79: 2021-04-01 | H79: 2009 | I79: PG-13 | J79: 164 min | K79: Comedies, Dramas, International Movies | L79: While attending one of India's premier colleges, three miserable engineering students and best friends struggle to beat the school's draconian system. | M79: 2021 | N79: =IF(AND(OR(YearFilter="All",$M79=YearFilter),OR(RatingFilter="All",$I79=RatingFilter),OR(TypeFilter="All",$B79=TypeFilter),OR(GenreFilter="All",COUNTIFS(tblGenre[show_id],$A79,tblGenre[Genre],GenreFilter)>0)),1,0)
A80: s1116 | B80: Movie | C80: Ferrari Ki Sawaari | D80: Rajesh Mapuskar | E80: Sharman Joshi, Boman Irani, Ritwik Sahore, Paresh Rawal, Deepak Shirke, Satyadeep Misra, Aakash Dabhade, Nilesh Diwekar, Vidya Balan | F80: India | G80: 2021-04-01 | H80: 2012 | I80: TV-PG | J80: 133 min | K80: Comedies, International Movies, Sports Movies | L80: A father winds up involved with a stolen Ferrari as he tries to acquire the money to send his son to the leading cricket academy. | M80: 2021 | N80: =IF(AND(OR(YearFilter="All",$M80=YearFilter),OR(RatingFilter="All",$I80=RatingFilter),OR(TypeFilter="All",$B80=TypeFilter),OR(GenreFilter="All",COUNTIFS(tblGenre[show_id],$A80,tblGenre[Genre],GenreFilter)>0)),1,0)
A81: s1123 | B81: Movie | C81: Madam Chief Minister | D81: Subhash Kapoor | E81: Richa Chadda, Saurabh Shukla, Manav Kaul, Shubrajyoti Barat, Akshay Oberoi, Boloram Das, Nikhil Vijay, Raviza Chauhan | F81: India | G81: 2021-04-01 | H81: 2020 | I81: TV-14 | J81: 121 min | K81: Dramas, International Movies | L81: Rising from disadvantage to become a state leader, a tenacious politician learns that with great power comes great responsibility, ruthlessness and risk. | M81: 2021 | N81: =IF(AND(OR(YearFilter="All",$M81=YearFilter),OR(RatingFilter="All",$I81=RatingFilter),OR(TypeFilter="All",$B81=TypeFilter),OR(GenreFilter="All",COUNTIFS(tblGenre[show_id],$A81,tblGenre[Genre],GenreFilter)>0)),1,0)
A82: s1142 | B82: Movie | C82: Wazir | D82: Bejoy Nambiar | E82: Amitabh Bachchan, Farhan Akhtar, Aditi Rao Hydari, Manav Kaul, Neil Nitin Mukesh, John Abraham | F82: India | G82: 2021-04-01 | H82: 2016 | I82: TV-14 | J82: 98 min | K82: Dramas, International Movies, Thrillers | L82: Helping an amputee grandmaster settle the score for his tragic past, a grieving detective unravels a conspiracy more complicated than he imagined. | M82: 2021 | N82: =IF(AND(OR(YearFilter="All",$M82=YearFilter),OR(RatingFilter="All",$I82=RatingFilter),OR(TypeFilter="All",$B82=TypeFilter),OR(GenreFilter="All",COUNTIFS(tblGenre[show_id],$A82,tblGenre[Genre],GenreFilter)>0)),1,0)
A83: s1166 | B83: Movie | C83: Pagglait | D83: Umesh Bist | E83: Sanya Malhotra, Sayani Gupta, Ashutosh Rana, Raghuvir Yadav, Shruti Sharma, Sheeba Chaddha, Natasha Rastogi, Rajesh Tailang, Meghna Malik, Jameel Khan, Chetan Sharma, Ananya Khare, Bhupesh Pandya | F83: India | G83: 2021-03-26 | H83: 2021 | I83: TV-PG | J83: 114 min | K83: Comedies, Dramas, International Movies | L83: Widowed soon after marriage, a young woman grapples with an inability to grieve, quirky relatives and a startling discovery about her late husband. | M83: 2021 | N83: =IF(AND(OR(YearFilter="All",$M83=YearFilter),OR(RatingFilter="All",$I83=RatingFilter),OR(TypeFilter="All",$B83=TypeFilter),OR(GenreFilter="All",COUNTIFS(tblGenre[show_id],$A83,tblGenre[Genre],GenreFilter)>0)),1,0)
A84: s1203 | B84: Movie | C84: C/O Kaadhal | D84: Hemambar Jasti | E84: Deepann, Vetri, Mumtaz Sorcar, Ayra, Karthik Rathnam, Sonia Giri, Nishesh, Shwetha | F84: India | G84: 2021-03-15 | H84: 2021 | I84: TV-14 | J84: 131 min | K84: Dramas, International Movies, Romantic Movies | L84: Cutting across conventions and expectations, four brave love stories blossom in this Tamil remake of the 2018 Telugu film "Care of Kancharapalem.” | M84: 2021 | N84: =IF(AND(OR(YearFilter="All",$M84=YearFilter),OR(RatingFilter="All",$I84=RatingFilter),OR(TypeFilter="All",$B84=TypeFilter),OR(GenreFilter="All",COUNTIFS(tblGenre[show_id],$A84,tblGenre[Genre],GenreFilter)>0)),1,0)
A85: s1204 | B85: Movie | C85: The BFG | D85: Steven Spielberg | E85: Mark Rylance, Ruby Barnhill, Penelope Wilton, Jemaine Clement, Rebecca Hall, Rafe Spall, Bill Hader, Ólafur Darri Ólafsson, Adam Godley, Michael Adamthwaite, Daniel Bacon, Jonathan Holmes, Chris Gibbs, Paul Moniz de Sa | F85: United States, India, United Kingdom | G85: 2021-03-15 | H85: 2016 | I85: PG | J85: 118 min | K85: Children & Family Movies, Dramas | L85: A little orphan meets up with a kind giant who's supposed to eat her but instead protects her from some truly horrible giants who terrorize them both. | M85: 2021 | N85: =IF(AND(OR(YearFilter="All",$M85=YearFilter),OR(RatingFilter="All",$I85=RatingFilter),OR(TypeFilter="All",$B85=TypeFilter),OR(GenreFilter="All",COUNTIFS(tblGenre[show_id],$A85,tblGenre[Genre],GenreFilter)>0)),1,0)
A86: s1228 | B86: TV Show | C86: Bombay Begums | E86: Pooja Bhatt, Shahana Goswami, Amruta Subhash, Plabita Borthakur, Aadhya Anand, Manish Chaudhary, Vivek Gomber, Danish Husain, Rahul Bose, Imaaduddin Shah, Sanghmitra Hitaishi | F86: India | G86: 2021-03-08 | H86: 2021 | I86: TV-MA | J86: 1 Season | K86: International TV Shows, TV Dramas | L86: From boardrooms to society's margins, five ambitious women from various walks of life navigate dreams, desires and disappointments in modern Mumbai. | M86: 2021 | N86: =IF(AND(OR(YearFilter="All",$M86=YearFilter),OR(RatingFilter="All",$I86=RatingFilter),OR(TypeFilter="All",$B86=TypeFilter),OR(GenreFilter="All",COUNTIFS(tblGenre[show_id],$A86,tblGenre[Genre],GenreFilter)>0)),1,0)
A87: s1229 | B87: Movie | C87: Bombay Rose | D87: Gitanjali Rao | E87: Cyli Khare, Gargi Shitole, Amardeep Jha, Amit Deondi, Makrand Deshpande, Virendra Saxena, Shishir Sharma | F87: India, United Kingdom, France, Qatar | G87: 2021-03-08 | H87: 2021 | I87: PG-13 | J87: 97 min | K87: Dramas, Independent Movies, International Movies | L87: Amidst the bustle of a magnetic and multifaceted city, the budding love between two dreamers is tested. | M87: 2021 | N87: =IF(AND(OR(YearFilter="All",$M87=YearFilter),OR(RatingFilter="All",$I87=RatingFilter),OR(TypeFilter="All",$B87=TypeFilter),OR(GenreFilter="All",COUNTIFS(tblGenre[show_id],$A87,tblGenre[Genre],GenreFilter)>0)),1,0)
A88: s1231 | B88: Movie | C88: Aelay | D88: Halitha Shameem | E88: P. Samuthirakani, Manikandan, Madhumathi Padmanathan, Akalyadevi B., S I Neelambari | F88: India | G88: 2021-03-05 | H88: 2021 | I88: TV-14 | J88: 151 min | K88: Comedies, Dramas, Independent Movies | L88: A son stoically returns to his village upon his father’s death, recalling their chilly dynamic before a bizarre event disrupts his visit. | M88: 2021 | N88: =IF(AND(OR(YearFilter="All",$M88=YearFilter),OR(RatingFilter="All",$I88=RatingFilter),OR(TypeFilter="All",$B88=TypeFilter),OR(GenreFilter="All",COUNTIFS(tblGenre[show_id],$A88,tblGenre[Genre],GenreFilter)>0)),1,0)
A89: s1245 | B89: Movie | C89: Indoo Ki Jawani | D89: Abir Sengupta | E89: Kiara Advani, Aditya Seal, Mallika Dua, Rakesh Bedi, Rajendra Sethi, Chittaranjan Tripathi, Rajesh Jais, Alka Badola Kaushal | F89: India | G89: 2021-03-02 | H89: 2020 | I89: TV-14 | J89: 115 min | K89: Action & Adventure, Comedies, International Movies | L89: A spirited but naive young woman seeks a one-night stand, but after discovering her date’s real identity, things quickly go from casual to complicated. | M89: 2021 | N89: =IF(AND(OR(YearFilter="All",$M89=YearFilter),OR(RatingFilter="All",$I89=RatingFilter),OR(TypeFilter="All",$B89=TypeFilter),OR(GenreFilter="All",COUNTIFS(tblGenre[show_id],$A89,tblGenre[Genre],GenreFilter)>0)),1,0)
A90: s1266 | B90: Movie | C90: The Girl on the Train | D90: Ribhu Dasgupta | E90: Parineeti Chopra, Aditi Rao Hydari, Kirti Kulhari, Avinash Tiwary, Tota Roy Chowdhury | F90: India | G90: 2021-02-26 | H90: 2021 | I90: TV-MA | J90: 120 min | K90: International Movies, Thrillers | L90: A troubled divorcée fixates on a seemingly ideal couple from afar until a shocking observation sends her spiraling straight into a knotty murder case. | M90: 2021 | N90: =IF(AND(OR(YearFilter="All",$M90=YearFilter),OR(RatingFilter="All",$I90=RatingFilter),OR(TypeFilter="All",$B90=TypeFilter),OR(GenreFilter="All",COUNTIFS(tblGenre[show_id],$A90,tblGenre[Genre],GenreFilter)>0)),1,0)
A91: s1282 | B91: Movie | C91: Red | D91: Tirumala Kishore | E91: Ram Pothineni, Nivetha Pethuraj, Malvika Sharma, Amritha Aiyer, Sampath Raj | F91: India | G91: 2021-02-23 | H91: 2021 | I91: TV-14 | J91: 143 min | K91: Dramas, International Movies | L91: A murder investigation leads police to a photo of a suspect, but when two men are found with faces that match the picture, the case gets doubly tricky. | M91: 2021 | N91: =IF(AND(OR(YearFilter="All",$M91=YearFilter),OR(RatingFilter="All",$I91=RatingFilter),OR(TypeFilter="All",$B91=TypeFilter),OR(GenreFilter="All",COUNTIFS(tblGenre[show_id],$A91,tblGenre[Genre],GenreFilter)>0)),1,0)
A92: s1283 | B92: TV Show | C92: Zindagi in Short | F92: India | G92: 2021-02-22 | H92: 2020 | I92: TV-MA | J92: 1 Season | K92: International TV Shows, TV Dramas | L92: Complicated marriages, digital romances, domestic dilemmas and schoolyard bullies get the spotlight in these seven, slice-of-life short films. | M92: 2021 | N92: =IF(AND(OR(YearFilter="All",$M92=YearFilter),OR(RatingFilter="All",$I92=RatingFilter),OR(TypeFilter="All",$B92=TypeFilter),OR(GenreFilter="All",COUNTIFS(tblGenre[show_id],$A92,tblGenre[Genre],GenreFilter)>0)),1,0)
A93: s1292 | B93: Movie | C93: Love | D93: Khalid Rahman | E93: Shine Tom Chacko, Rajisha Vijayan, Gokulan, Sudhi Koppa, Veena Nandakumar, Johny Antony | F93: India | G93: 2021-02-19 | H93: 2020 | I93: TV-14 | J93: 91 min | K93: Dramas, Independent Movies, International Movies | L93: The troubling inner workings of a toxic marriage reveal themselves in surprising ways after one of the couple’s feuds spins out of control. | M93: 2021 | N93: =IF(AND(OR(YearFilter="All",$M93=YearFilter),OR(RatingFilter="All",$I93=RatingFilter),OR(TypeFilter="All",$B93=TypeFilter),OR(GenreFilter="All",COUNTIFS(tblGenre[show_id],$A93,tblGenre[Genre],GenreFilter)>0)),1,0)
A94: s1294 | B94: TV Show | C94: Pitta Kathalu | D94: Tharun Bhascker Dhaassyam, B. V. Nandini Reddy, Nag Ashwin, Sankalp Reddy | E94: Manchu Lakshmi, Saanve Megghana, Naveen Kumar, Jagapathi Babu, Amala Paul, Aswin Kakamanu, Shruthi Haasan, Sanjith Hegde, Sangeeth Shoban, Anish Kuruvilla, Uko, Dayanand Reddy, Thanmayi, Satya Dev, Eesha Rebba, Srinivas Avasarala, Ashima Narwal | F94: India | G94: 2021-02-19 | H94: 2021 | I94: TV-MA | J94: 1 Season | K94: International TV Shows, TV Dramas | L94: From secrets and lies to jealousy and control, four stories in this anthology film explore the darker, deceptive sides of love. | M94: 2021 | N94: =IF(AND(OR(YearFilter="All",$M94=YearFilter),OR(RatingFilter="All",$I94=RatingFilter),OR(TypeFilter="All",$B94=TypeFilter),OR(GenreFilter="All",COUNTIFS(tblGenre[show_id],$A94,tblGenre[Genre],GenreFilter)>0)),1,0)
A95: s1296 | B95: Movie | C95: Eeb Allay Ooo! | D95: Prateek Vats | E95: Shardul Bhardwaj, Nutan Sinha, Shashi Bhushan, Mahinder Nath, Nitin Goel, Naina Sareen | F95: India | G95: 2021-02-18 | H95: 2019 | I95: TV-MA | J95: 97 min | K95: Comedies, Dramas, Independent Movies | L95: Hired as a monkey repeller upon moving to Delhi, a young man struggles to find his footing in his unenviable job and his place in the unforgiving world. | M95: 2021 | N95: =IF(AND(OR(YearFilter="All",$M95=YearFilter),OR(RatingFilter="All",$I95=RatingFilter),OR(TypeFilter="All",$B95=TypeFilter),OR(GenreFilter="All",COUNTIFS(tblGenre[show_id],$A95,tblGenre[Genre],GenreFilter)>0)),1,0)
A96: s1306 | B96: Movie | C96: Awara Paagal Deewana | D96: Vikram Bhatt | E96: Akshay Kumar, Sunil Shetty, Aftab Shivdasani, Preeti Jhangiani, Amrita Arora, Aarti Chhabria, Paresh Rawal, Johny Lever, Rahul Dev, Supriya Pilgaonkar | F96: India | G96: 2021-02-16 | H96: 2002 | I96: TV-14 | J96: 162 min | K96: Action & Adventure, Comedies, Dramas | L96: A dentist unwittingly becomes caught in the madcap fight between two criminal brothers-in-law trying to kill one another off to claim their inheritance. | M96: 2021 | N96: =IF(AND(OR(YearFilter="All",$M96=YearFilter),OR(RatingFilter="All",$I96=RatingFilter),OR(TypeFilter="All",$B96=TypeFilter),OR(GenreFilter="All",COUNTIFS(tblGenre[show_id],$A96,tblGenre[Genre],GenreFilter)>0)),1,0)
A97: s1317 | B97: Movie | C97: Mundina Nildana | D97: Vinay Bharadwaj | E97: Praveen Tej, Radhika Narayan, Ananya Kashyap, Ajay Raj, Dattanna, Shankar Ashwath, Kshama Santosh Rai, Diksha Sharma | F97: India | G97: 2021-02-12 | H97: 2019 | I97: TV-MA | J97: 104 min | K97: Dramas, International Movies, Romantic Movies | L97: As three young professionals chase their wildly different dreams, their relationships with each other indelibly impact their journeys of self-discovery. | M97: 2021 | N97: =IF(AND(OR(YearFilter="All",$M97=YearFilter),OR(RatingFilter="All",$I97=RatingFilter),OR(TypeFilter="All",$B97=TypeFilter),OR(GenreFilter="All",COUNTIFS(tblGenre[show_id],$A97,tblGenre[Genre],GenreFilter)>0)),1,0)
A98: s1377 | B98: Movie | C98: Kilometers and Kilometers | D98: Jeo Baby | E98: Tovino Thomas, India Jarvis, Joju George, Sidhartha Siva, Basil Joseph, Sudheesh, Parvathi T, Pauly Valsan | F98: India | G98: 2021-01-27 | H98: 2020 | I98: TV-MA | J98: 127 min | K98: Comedies, Dramas, Independent Movies | L98: When a debt-ridden man reluctantly agrees to drive an American tourist around India, their stark differences lead to bickering… and unexpected bonding. | M98: 2021 | N98: =IF(AND(OR(YearFilter="All",$M98=YearFilter),OR(RatingFilter="All",$I98=RatingFilter),OR(TypeFilter="All",$B98=TypeFilter),OR(GenreFilter="All",COUNTIFS(tblGenre[show_id],$A98,tblGenre[Genre],GenreFilter)>0)),1,0)
A99: s1389 | B99: Movie | C99: The White Tiger | D99: Ramin Bahrani | E99: Adarsh Gourav, Rajkummar Rao, Priyanka Chopra Jonas, Mahesh Manjrekar, Vijay Maurya | F99: India, United States | G99: 2021-01-22 | H99: 2021 | I99: R | J99: 127 min | K99: Dramas | L99: The ambitious driver for a rich Indian family uses his wit and cunning to escape from poverty and become an entrepreneur. Based on the bestselling novel. | M99: 2021 | N99: =IF(AND(OR(YearFilter="All",$M99=YearFilter),OR(RatingFilter="All",$I99=RatingFilter),OR(TypeFilter="All",$B99=TypeFilter),OR(GenreFilter="All",COUNTIFS(tblGenre[show_id],$A99,tblGenre[Genre],GenreFilter)>0)),1,0)
A100: s1411 | B100: Movie | C100: Tribhanga - Tedhi Medhi Crazy | D100: Renuka Shahane | E100: Kajol, Tanvi Azmi, Mithila Palkar, Kunaal Roy Kapur, Vaibhav Tatwawaadi, Kanwaljeet Singh, Manav Gohil, Shweta Mehendale | F100: India | G100: 2021-01-15 | H100: 2021 | I100: TV-MA | J100: 96 min | K100: Dramas, International Movies | L100: When her estranged mother falls into a coma, a self-made single mom grapples with regret and resentment while reflecting on their strained relationship. | M100: 2021 | N100: =IF(AND(OR(YearFilter="All",$M100=YearFilter),OR(RatingFilter="All",$I100=RatingFilter),OR(TypeFilter="All",$B100=TypeFilter),OR(GenreFilter="All",COUNTIFS(tblGenre[show_id],$A100,tblGenre[Genre],GenreFilter)>0)),1,0)
A101: s1423 | B101: Movie | C101: Apaharan | D101: Prakash Jha | E101: Ajay Devgn, Nana Patekar, Bipasha Basu, Ayub Khan, Mohan Agashe, Mukesh Tiwari, Yashpal Sharma, Anoop Soni, Chetan Pandit | F101: India | G101: 2021-01-08 | H101: 2005 | I101: TV-14 | J101: 161 min | K101: Dramas, International Movies | L101: Raised under the condescending eye of his activist father, an underachieving loafer is lured into the local kingpin’s web of corruption and kidnapping. | M101: 2021 | N101: =IF(AND(OR(YearFilter="All",$M101=YearFilter),OR(RatingFilter="All",$I101=RatingFilter),OR(TypeFilter="All",$B101=TypeFilter),OR(GenreFilter="All",COUNTIFS(tblGenre[show_id],$A101,tblGenre[Genre],GenreFilter)>0)),1,0)
A102: s1424 | B102: Movie | C102: BluffMaster! | D102: Rohan Sippy | E102: Abhishek Bachchan, Priyanka Chopra, Riteish Deshmukh, Boman Irani, Nana Patekar, Sanjay Mishra, Tinnu Anand, Hussain Shaikh | F102: India | G102: 2021-01-08 | H102: 2005 | I102: TV-14 | J102: 129 min | K102: Comedies, International Movies, Romantic Movies | L102: When his girlfriend learns the truth about his murky past, a con artist is forced to examine his choices and get to the root of his real identity. | M102: 2021 | N102: =IF(AND(OR(YearFilter="All",$M102=YearFilter),OR(RatingFilter="All",$I102=RatingFilter),OR(TypeFilter="All",$B102=TypeFilter),OR(GenreFilter="All",COUNTIFS(tblGenre[show_id],$A102,tblGenre[Genre],GenreFilter)>0)),1,0)
A103: s1427 | B103: Movie | C103: Gangaajal | D103: Prakash Jha | E103: Ajay Devgn, Gracy Singh, Mohan Agashe, Mohan Joshi, Ayub Khan, Akhilendra Mishra, Mukesh Tiwari, Yashpal Sharma, Brij Gopal, Anita Kanwal | F103: India | G103: 2021-01-08 | H103: 2003 | I103: TV-MA | J103: 148 min | K103: Dramas, International Movies | L103: Posted to a small, crime-ridden town, a cop soon learns that cleaning up the system also means confronting the corruption among police and politicians. | M103: 2021 | N103: =IF(AND(OR(YearFilter="All",$M103=YearFilter),OR(RatingFilter="All",$I103=RatingFilter),OR(TypeFilter="All",$B103=TypeFilter),OR(GenreFilter="All",COUNTIFS(tblGenre[show_id],$A103,tblGenre[Genre],GenreFilter)>0)),1,0)
A104: s1429 | B104: Movie | C104: Is Love Enough? Sir | D104: Rohena Gera | E104: Tillotama Shome, Vivek Gomber, Geetanjali Kulkarni, Rahul Vohra, Divya Seth, Chandrachoor Rai, Dilnaz Irani, Bhagyashree Pandit, Anupriya Goenka, Rashi Mal | F104: India, France | G104: 2021-01-08 | H104: 2018 | I104: TV-MA | J104: 99 min | K104: Dramas, Independent Movies, International Movies | L104: A young widow is hired as the domestic helper for a wealthy architect, but social divides come to the fore as an unlikely attraction grows between them. | M104: 2021 | N104: =IF(AND(OR(YearFilter="All",$M104=YearFilter),OR(RatingFilter="All",$I104=RatingFilter),OR(TypeFilter="All",$B104=TypeFilter),OR(GenreFilter="All",COUNTIFS(tblGenre[show_id],$A104,tblGenre[Genre],GenreFilter)>0)),1,0)
A105: s1430 | B105: TV Show | C105: Mighty Little Bheem: Kite Festival | E105: Sumruddhi Shukla, Aranya Kaur, Nishka Raheja | F105: India | G105: 2021-01-08 | H105: 2021 | I105: TV-Y | J105: 1 Season | K105: Kids' TV, TV Comedies | L105: With winter behind them, Bheem and his townspeople usher in a sunny new season in all their favorite ways during the Makar Sankranti festival. | M105: 2021 | N105: =IF(AND(OR(YearFilter="All",$M105=YearFilter),OR(RatingFilter="All",$I105=RatingFilter),OR(TypeFilter="All",$B105=TypeFilter),OR(GenreFilter="All",COUNTIFS(tblGenre[show_id],$A105,tblGenre[Genre],GenreFilter)>0)),1,0)
A106: s1442 | B106: Movie | C106: Hello Brother | D106: Sohail Khan | E106: Salman Khan, Arbaaz Khan, Rani Mukerji, Johny Lever, Neeraj Vora, Shakti Kapoor, Razak Khan, Sulabha Arya | F106: India | G106: 2021-01-04 | H106: 1999 | I106: TV-14 | J106: 126 min | K106: Action & Adventure, Comedies, International Movies | L106: After receiving a heart transplant from a murdered man, a cop is followed around by the victim’s ghost, who won’t rest until his death has been avenged. | M106: 2021 | N106: =IF(AND(OR(YearFilter="All",$M106=YearFilter),OR(RatingFilter="All",$I106=RatingFilter),OR(TypeFilter="All",$B106=TypeFilter),OR(GenreFilter="All",COUNTIFS(tblGenre[show_id],$A106,tblGenre[Genre],GenreFilter)>0)),1,0)
A107: s1473 | B107: Movie | C107: Bobby Jasoos | D107: Samar Shaikh | E107: Vidya Balan, Ali Fazal, Supriya Pathak, Tanvi Azmi, Zarina Wahab, Kiran Kumar, Rajendra Gupta, Arjan Bajwa, Prasad Barve, Aakash Dahiya | F107: India | G107: 2020-12-31 | H107: 2014 | I107: TV-14 | J107: 116 min | K107: Comedies, Dramas, International Movies | L107: With unlimited determination and zero field experience, a small-town detective accepts a lucrative case from a mysterious – and suspicious – stranger. | M107: 2020 | N107: =IF(AND(OR(YearFilter="All",$M107=YearFilter),OR(RatingFilter="All",$I107=RatingFilter),OR(TypeFilter="All",$B107=TypeFilter),OR(GenreFilter="All",COUNTIFS(tblGenre[show_id],$A107,tblGenre[Genre],GenreFilter)>0)),1,0)
A108: s1490 | B108: TV Show | C108: Regiment Diaries | F108: India | G108: 2020-12-26 | H108: 2020 | I108: TV-PG | J108: 2 Seasons | K108: Docuseries, International TV Shows | L108: Historical footage and interviews with soldiers showcase war stories, unique traditions and unifying principles of the Indian Army’s various regiments. | M108: 2020 | N108: =IF(AND(OR(YearFilter="All",$M108=YearFilter),OR(RatingFilter="All",$I108=RatingFilter),OR(TypeFilter="All",$B108=TypeFilter),OR(GenreFilter="All",COUNTIFS(tblGenre[show_id],$A108,tblGenre[Genre],GenreFilter)>0)),1,0)
A109: s1492 | B109: Movie | C109: AK vs AK | D109: Vikramaditya Motwane | E109: Anil Kapoor, Anurag Kashyap | F109: India | G109: 2020-12-25 | H109: 2020 | I109: TV-MA | J109: 109 min | K109: Comedies, Dramas, International Movies | L109: After a public spat with a movie star, a disgraced director retaliates by kidnapping the actor’s daughter, filming the search for her in real time. | M109: 2020 | N109: =IF(AND(OR(YearFilter="All",$M109=YearFilter),OR(RatingFilter="All",$I109=RatingFilter),OR(TypeFilter="All",$B109=TypeFilter),OR(GenreFilter="All",COUNTIFS(tblGenre[show_id],$A109,tblGenre[Genre],GenreFilter)>0)),1,0)
A110: s1521 | B110: TV Show | C110: Paava Kadhaigal | D110: Sudha Kongara, Vignesh Shivan, Gautham Vasudev Menon, Vetri Maaran | E110: Kalidas Jayaram, Shanthnu Bhagyaraj, Bhavani Sre, Kalki Koechlin, Anjali, Padam Kumar, Prakash Raj, Sai Pallavi, Hari, Gautham Vasudev Menon, Simran | F110: India | G110: 2020-12-18 | H110: 2020 | I110: TV-MA | J110: 1 Season | K110: International TV Shows, TV Dramas | L110: At times dark, at times disturbing, four short films explore stories of those who dare to dream and desire — and those determined to stand in their way. | M110: 2020 | N110: =IF(AND(OR(YearFilter="All",$M110=YearFilter),OR(RatingFilter="All",$I110=RatingFilter),OR(TypeFilter="All",$B110=TypeFilter),OR(GenreFilter="All",COUNTIFS(tblGenre[show_id],$A110,tblGenre[Genre],GenreFilter)>0)),1,0)
A111: s1543 | B111: Movie | C111: Vir Das: Outside In - The Lockdown Special | D111: Vir Das | E111: Vir Das | F111: India | G111: 2020-12-16 | H111: 2020 | I111: TV-MA | J111: 50 min | K111: Stand-Up Comedy | L111: Stage banter takes on a different — deeper — meaning as the comedian performs online shows to homebound viewers worldwide from his Mumbai residence. | M111: 2020 | N111: =IF(AND(OR(YearFilter="All",$M111=YearFilter),OR(RatingFilter="All",$I111=RatingFilter),OR(TypeFilter="All",$B111=TypeFilter),OR(GenreFilter="All",COUNTIFS(tblGenre[show_id],$A111,tblGenre[Genre],GenreFilter)>0)),1,0)
A112: s1562 | B112: Movie | C112: Torbaaz | D112: Girish Malik | E112: Sanjay Dutt, Nargis Fakhri, Rahul Dev, Priyanka Verma, Kuwaarjeet Chopraa, Aishan Jawaid Malik, Rahul Mittra, Gavie Chahal, Humayun Shams Khan, Babrak Akbari | F112: India | G112: 2020-12-11 | H112: 2020 | I112: TV-MA | J112: 133 min | K112: Dramas, International Movies, Sports Movies | L112: At an Afghanistan refugee camp, an ex-army doctor seeks to bring children joy through cricket — and soon realizes that the stakes go beyond the sport. | M112: 2020 | N112: =IF(AND(OR(YearFilter="All",$M112=YearFilter),OR(RatingFilter="All",$I112=RatingFilter),OR(TypeFilter="All",$B112=TypeFilter),OR(GenreFilter="All",COUNTIFS(tblGenre[show_id],$A112,tblGenre[Genre],GenreFilter)>0)),1,0)
A113: s1590 | B113: TV Show | C113: Bhaag Beanie Bhaag | E113: Swara Bhasker, Dolly Singh, Ravi Patel, Varun Thakur, Mona Ambegaonkar, Girish Kulkarni | F113: India | G113: 2020-12-04 | H113: 2020 | I113: TV-MA | J113: 1 Season | K113: International TV Shows, Romantic TV Shows, TV Comedies | L113: Facing disapproving parents, a knotty love life and her own inner critic, an aspiring comic ditches her cushy but unsatisfying life to pursue stand-up. | M113: 2020 | N113: =IF(AND(OR(YearFilter="All",$M113=YearFilter),OR(RatingFilter="All",$I113=RatingFilter),OR(TypeFilter="All",$B113=TypeFilter),OR(GenreFilter="All",COUNTIFS(tblGenre[show_id],$A113,tblGenre[Genre],GenreFilter)>0)),1,0)
A114: s1619 | B114: TV Show | C114: Octonauts | E114: Keith Wickham, Jo Wyatt, Ross Breen, Simon Greenall, Paul Panting, Rob Rackstraw, Teresa Gallagher, Shelley Longworth | F114: United States, Ireland, United Kingdom, India | G114: 2020-12-01 | H114: 2015 | I114: TV-Y | J114: 4 Seasons | K114: British TV Shows, Kids' TV | L114: A team of brave underwater explorers known as the Octonauts combs the world's oceans for aquatic creatures in desperate need of assistance. | M114: 2020 | N114: =IF(AND(OR(YearFilter="All",$M114=YearFilter),OR(RatingFilter="All",$I114=RatingFilter),OR(TypeFilter="All",$B114=TypeFilter),OR(GenreFilter="All",COUNTIFS(tblGenre[show_id],$A114,tblGenre[Genre],GenreFilter)>0)),1,0)
A115: s1639 | B115: TV Show | C115: Fabulous Lives of Bollywood Wives | F115: India | G115: 2020-11-27 | H115: 2020 | I115: TV-MA | J115: 1 Season | K115: International TV Shows, Reality TV | L115: Cameras follow the banter and bonding between four fun-loving women from Bollywood’s inner circle as they juggle professions, family and friendship. | M115: 2020 | N115: =IF(AND(OR(YearFilter="All",$M115=YearFilter),OR(RatingFilter="All",$I115=RatingFilter),OR(TypeFilter="All",$B115=TypeFilter),OR(GenreFilter="All",COUNTIFS(tblGenre[show_id],$A115,tblGenre[Genre],GenreFilter)>0)),1,0)
...

Sheet Genre_Data
A1: show_id | B1: Genre | C1: Type_lookup | D1: Rating_lookup | E1: YearAdded_lookup | F1: IncludeRow_NoGenre
A2: s5 | B2: International TV Shows | C2: =IFERROR(INDEX(tblNetflix[type],MATCH($A2,tblNetflix[show_id],0)),"") | D2: =IFERROR(INDEX(tblNetflix[rating],MATCH($A2,tblNetflix[show_id],0)),"") | E2: =IFERROR(INDEX(tblNetflix[year_added],MATCH($A2,tblNetflix[show_id],0)),"") | F2: =IF(AND(OR(YearFilter="All",$E2=YearFilter),OR(RatingFilter="All",$D2=RatingFilter),OR(TypeFilter="All",$C2=TypeFilter)),1,0)
A3: s5 | B3: Romantic TV Shows | C3: =IFERROR(INDEX(tblNetflix[type],MATCH($A3,tblNetflix[show_id],0)),"") | D3: =IFERROR(INDEX(tblNetflix[rating],MATCH($A3,tblNetflix[show_id],0)),"") | E3: =IFERROR(INDEX(tblNetflix[year_added],MATCH($A3,tblNetflix[show_id],0)),"") | F3: =IF(AND(OR(YearFilter="All",$E3=YearFilter),OR(RatingFilter="All",$D3=RatingFilter),OR(TypeFilter="All",$C3=TypeFilter)),1,0)
A4: s5 | B4: TV Comedies | C4: =IFERROR(INDEX(tblNetflix[type],MATCH($A4,tblNetflix[show_id],0)),"") | D4: =IFERROR(INDEX(tblNetflix[rating],MATCH($A4,tblNetflix[show_id],0)),"") | E4: =IFERROR(INDEX(tblNetflix[year_added],MATCH($A4,tblNetflix[show_id],0)),"") | F4: =IF(AND(OR(YearFilter="All",$E4=YearFilter),OR(RatingFilter="All",$D4=RatingFilter),OR(TypeFilter="All",$C4=TypeFilter)),1,0)
A5: s25 | B5: Comedies | C5: =IFERROR(INDEX(tblNetflix[type],MATCH($A5,tblNetflix[show_id],0)),"") | D5: =IFERROR(INDEX(tblNetflix[rating],MATCH($A5,tblNetflix[show_id],0)),"") | E5: =IFERROR(INDEX(tblNetflix[year_added],MATCH($A5,tblNetflix[show_id],0)),"") | F5: =IF(AND(OR(YearFilter="All",$E5=YearFilter),OR(RatingFilter="All",$D5=RatingFilter),OR(TypeFilter="All",$C5=TypeFilter)),1,0)
A6: s25 | B6: International Movies | C6: =IFERROR(INDEX(tblNetflix[type],MATCH($A6,tblNetflix[show_id],0)),"") | D6: =IFERROR(INDEX(tblNetflix[rating],MATCH($A6,tblNetflix[show_id],0)),"") | E6: =IFERROR(INDEX(tblNetflix[year_added],MATCH($A6,tblNetflix[show_id],0)),"") | F6: =IF(AND(OR(YearFilter="All",$E6=YearFilter),OR(RatingFilter="All",$D6=RatingFilter),OR(TypeFilter="All",$C6=TypeFilter)),1,0)
A7: s25 | B7: Romantic Movies | C7: =IFERROR(INDEX(tblNetflix[type],MATCH($A7,tblNetflix[show_id],0)),"") | D7: =IFERROR(INDEX(tblNetflix[rating],MATCH($A7,tblNetflix[show_id],0)),"") | E7: =IFERROR(INDEX(tblNetflix[year_added],MATCH($A7,tblNetflix[show_id],0)),"") | F7: =IF(AND(OR(YearFilter="All",$E7=YearFilter),OR(RatingFilter="All",$D7=RatingFilter),OR(TypeFilter="All",$C7=TypeFilter)),1,0)
A8: s30 | B8: Thrillers | C8: =IFERROR(INDEX(tblNetflix[type],MATCH($A8,tblNetflix[show_id],0)),"") | D8: =IFERROR(INDEX(tblNetflix[rating],MATCH($A8,tblNetflix[show_id],0)),"") | E8: =IFERROR(INDEX(tblNetflix[year_added],MATCH($A8,tblNetflix[show_id],0)),"") | F8: =IF(AND(OR(YearFilter="All",$E8=YearFilter),OR(RatingFilter="All",$D8=RatingFilter),OR(TypeFilter="All",$C8=TypeFilter)),1,0)
A9: s40 | B9: Kids' TV | C9: =IFERROR(INDEX(tblNetflix[type],MATCH($A9,tblNetflix[show_id],0)),"") | D9: =IFERROR(INDEX(tblNetflix[rating],MATCH($A9,tblNetflix[show_id],0)),"") | E9: =IFERROR(INDEX(tblNetflix[year_added],MATCH($A9,tblNetflix[show_id],0)),"") | F9: =IF(AND(OR(YearFilter="All",$E9=YearFilter),OR(RatingFilter="All",$D9=RatingFilter),OR(TypeFilter="All",$C9=TypeFilter)),1,0)
A10: s51 | B10: International TV Shows | C10: =IFERROR(INDEX(tblNetflix[type],MATCH($A10,tblNetflix[show_id],0)),"") | D10: =IFERROR(INDEX(tblNetflix[rating],MATCH($A10,tblNetflix[show_id],0)),"") | E10: =IFERROR(INDEX(tblNetflix[year_added],MATCH($A10,tblNetflix[show_id],0)),"") | F10: =IF(AND(OR(YearFilter="All",$E10=YearFilter),OR(RatingFilter="All",$D10=RatingFilter),OR(TypeFilter="All",$C10=TypeFilter)),1,0)
A11: s51 | B11: TV Dramas | C11: =IFERROR(INDEX(tblNetflix[type],MATCH($A11,tblNetflix[show_id],0)),"") | D11: =IFERROR(INDEX(tblNetflix[rating],MATCH($A11,tblNetflix[show_id],0)),"") | E11: =IFERROR(INDEX(tblNetflix[year_added],MATCH($A11,tblNetflix[show_id],0)),"") | F11: =IF(AND(OR(YearFilter="All",$E11=YearFilter),OR(RatingFilter="All",$D11=RatingFilter),OR(TypeFilter="All",$C11=TypeFilter)),1,0)
A12: s51 | B12: TV Sci-Fi & Fantasy | C12: =IFERROR(INDEX(tblNetflix[type],MATCH($A12,tblNetflix[show_id],0)),"") | D12: =IFERROR(INDEX(tblNetflix[rating],MATCH($A12,tblNetflix[show_id],0)),"") | E12: =IFERROR(INDEX(tblNetflix[year_added],MATCH($A12,tblNetflix[show_id],0)),"") | F12: =IF(AND(OR(YearFilter="All",$E12=YearFilter),OR(RatingFilter="All",$D12=RatingFilter),OR(TypeFilter="All",$C12=TypeFilter)),1,0)
A13: s67 | B13: Docuseries | C13: =IFERROR(INDEX(tblNetflix[type],MATCH($A13,tblNetflix[show_id],0)),"") | D13: =IFERROR(INDEX(tblNetflix[rating],MATCH($A13,tblNetflix[show_id],0)),"") | E13: =IFERROR(INDEX(tblNetflix[year_added],MATCH($A13,tblNetflix[show_id],0)),"") | F13: =IF(AND(OR(YearFilter="All",$E13=YearFilter),OR(RatingFilter="All",$D13=RatingFilter),OR(TypeFilter="All",$C13=TypeFilter)),1,0)
... A2805: s8807 | B2805: Music & Musicals | C2805: =IFERROR(INDEX(tblNetflix[type],MATCH($A2805,tblNetflix[show_id],0)),"") | D2805: =IFERROR(INDEX(tblNetflix[rating],MATCH($A2805,tblNetflix[show_id],0)),"") | E2805: =IFERROR(INDEX(tblNetflix[year_added],MATCH($A2805,tblNetflix[show_id],0)),"") | F2805: =IF(AND(OR(YearFilter="All",$E2805=YearFilter),OR(RatingFilter="All",$D2805=RatingFilter),OR(TypeFilter="All",$C2805=TypeFilter)),1,0)

Sheet Theme_Data
A1: title | B1: description | C1: Theme | D1: Type_lookup | E1: Rating_lookup | F1: YearAdded_lookup | G1: IncludeRow
A2: Kota Factory | B2: In a city of coaching centers known to train India’s finest collegiate minds, an earnest but unexceptional student and his friends navigate campus life. | C2: Education & Youth | D2: =IFERROR(INDEX(tblNetflix[type],MATCH($A2,tblNetflix[title],0)),"") | E2: =IFERROR(INDEX(tblNetflix[rating],MATCH($A2,tblNetflix[title],0)),"") | F2: =IFERROR(INDEX(tblNetflix[year_added],MATCH($A2,tblNetflix[title],0)),"") | G2: =IF(AND(OR(YearFilter="All",$F2=YearFilter),OR(RatingFilter="All",$E2=RatingFilter),OR(TypeFilter="All",$D2=TypeFilter)),1,0)
A3: Jeans | B3: When the father of the man she loves insists that his twin sons marry twin sisters, a woman creates an alter ego that might be a bit too convincing. | C3: Romance | D3: =IFERROR(INDEX(tblNetflix[type],MATCH($A3,tblNetflix[title],0)),"") | E3: =IFERROR(INDEX(tblNetflix[rating],MATCH($A3,tblNetflix[title],0)),"") | F3: =IFERROR(INDEX(tblNetflix[year_added],MATCH($A3,tblNetflix[title],0)),"") | G3: =IF(AND(OR(YearFilter="All",$F3=YearFilter),OR(RatingFilter="All",$E3=RatingFilter),OR(TypeFilter="All",$D3=TypeFilter)),1,0)
A4: Paranoia | B4: Blackmailed by his company's CEO, a low-level employee finds himself forced to spy on the boss's rival and former mentor. | C4: Crime & Thriller | D4: =IFERROR(INDEX(tblNetflix[type],MATCH($A4,tblNetflix[title],0)),"") | E4: =IFERROR(INDEX(tblNetflix[rating],MATCH($A4,tblNetflix[title],0)),"") | F4: =IFERROR(INDEX(tblNetflix[year_added],MATCH($A4,tblNetflix[title],0)),"") | G4: =IF(AND(OR(YearFilter="All",$F4=YearFilter),OR(RatingFilter="All",$E4=RatingFilter),OR(TypeFilter="All",$D4=TypeFilter)),1,0)
A5: Chhota Bheem | B5: A brave, energetic little boy with superhuman powers leads his friends on exciting adventures to guard their fellow Dholakpur villagers from evil. | C5: Family & Children | D5: =IFERROR(INDEX(tblNetflix[type],MATCH($A5,tblNetflix[title],0)),"") | E5: =IFERROR(INDEX(tblNetflix[rating],MATCH($A5,tblNetflix[title],0)),"") | F5: =IFERROR(INDEX(tblNetflix[year_added],MATCH($A5,tblNetflix[title],0)),"") | G5: =IF(AND(OR(YearFilter="All",$F5=YearFilter),OR(RatingFilter="All",$E5=RatingFilter),OR(TypeFilter="All",$D5=TypeFilter)),1,0)
A6: Dharmakshetra | B6: After the ancient Great War, the god Chitragupta oversees a trial to determine who were the battle's true heroes and villains. | C6: Historical & Cultural | D6: =IFERROR(INDEX(tblNetflix[type],MATCH($A6,tblNetflix[title],0)),"") | E6: =IFERROR(INDEX(tblNetflix[rating],MATCH($A6,tblNetflix[title],0)),"") | F6: =IFERROR(INDEX(tblNetflix[year_added],MATCH($A6,tblNetflix[title],0)),"") | G6: =IF(AND(OR(YearFilter="All",$F6=YearFilter),OR(RatingFilter="All",$E6=RatingFilter),OR(TypeFilter="All",$D6=TypeFilter)),1,0)
A7: Raja Rasoi Aur Anya Kahaniyan | B7: Explore the history and flavors of regional Indian cuisine, from traditional Kashmiri feasts to the vegetarian dishes of Gujarat. | C7: Historical & Cultural | D7: =IFERROR(INDEX(tblNetflix[type],MATCH($A7,tblNetflix[title],0)),"") | E7: =IFERROR(INDEX(tblNetflix[rating],MATCH($A7,tblNetflix[title],0)),"") | F7: =IFERROR(INDEX(tblNetflix[year_added],MATCH($A7,tblNetflix[title],0)),"") | G7: =IF(AND(OR(YearFilter="All",$F7=YearFilter),OR(RatingFilter="All",$E7=RatingFilter),OR(TypeFilter="All",$D7=TypeFilter)),1,0)
A8: Stories by Rabindranath Tagore | B8: The writings of Nobel Prize winner Rabindranath Tagore come to life in this collection of tales set in early-20th-century Bengal. | C8: Historical & Cultural | D8: =IFERROR(INDEX(tblNetflix[type],MATCH($A8,tblNetflix[title],0)),"") | E8: =IFERROR(INDEX(tblNetflix[rating],MATCH($A8,tblNetflix[title],0)),"") | F8: =IFERROR(INDEX(tblNetflix[year_added],MATCH($A8,tblNetflix[title],0)),"") | G8: =IF(AND(OR(YearFilter="All",$F8=YearFilter),OR(RatingFilter="All",$E8=RatingFilter),OR(TypeFilter="All",$D8=TypeFilter)),1,0)
A9: Angamaly Diaries | B9: After growing up amidst the gang wars of his hometown, Vincent forms an entrepreneurial squad of his own and ends up on the wrong side of the law. | C9: Crime & Thriller | D9: =IFERROR(INDEX(tblNetflix[type],MATCH($A9,tblNetflix[title],0)),"") | E9: =IFERROR(INDEX(tblNetflix[rating],MATCH($A9,tblNetflix[title],0)),"") | F9: =IFERROR(INDEX(tblNetflix[year_added],MATCH($A9,tblNetflix[title],0)),"") | G9: =IF(AND(OR(YearFilter="All",$F9=YearFilter),OR(RatingFilter="All",$E9=RatingFilter),OR(TypeFilter="All",$D9=TypeFilter)),1,0)
A10: Anjaam | B10: A wealthy industrialist’s dangerous obsession with a flight attendant destroys her world, until she takes matters into her own hands to exact revenge. | C10: Crime & Thriller | D10: =IFERROR(INDEX(tblNetflix[type],MATCH($A10,tblNetflix[title],0)),"") | E10: =IFERROR(INDEX(tblNetflix[rating],MATCH($A10,tblNetflix[title],0)),"") | F10: =IFERROR(INDEX(tblNetflix[year_added],MATCH($A10,tblNetflix[title],0)),"") | G10: =IF(AND(OR(YearFilter="All",$F10=YearFilter),OR(RatingFilter="All",$E10=RatingFilter),OR(TypeFilter="All",$D10=TypeFilter)),1,0)
A11: Dhanak | B11: A movie-loving 10-year-old and her blind little brother trek to meet Indian superstar Shah Rukh Khan for help in getting the boy an eye operation. | C11: Family & Children | D11: =IFERROR(INDEX(tblNetflix[type],MATCH($A11,tblNetflix[title],0)),"") | E11: =IFERROR(INDEX(tblNetflix[rating],MATCH($A11,tblNetflix[title],0)),"") | F11: =IFERROR(INDEX(tblNetflix[year_added],MATCH($A11,tblNetflix[title],0)),"") | G11: =IF(AND(OR(YearFilter="All",$F11=YearFilter),OR(RatingFilter="All",$E11=RatingFilter),OR(TypeFilter="All",$D11=TypeFilter)),1,0)
A12: Gurgaon | B12: When the daughter of a wealthy family returns from college, she gets a frosty welcome from her brother, who has problems – and plans – of his own. | C12: Family & Children | D12: =IFERROR(INDEX(tblNetflix[type],MATCH($A12,tblNetflix[title],0)),"") | E12: =IFERROR(INDEX(tblNetflix[rating],MATCH($A12,tblNetflix[title],0)),"") | F12: =IFERROR(INDEX(tblNetflix[year_added],MATCH($A12,tblNetflix[title],0)),"") | G12: =IF(AND(OR(YearFilter="All",$F12=YearFilter),OR(RatingFilter="All",$E12=RatingFilter),OR(TypeFilter="All",$D12=TypeFilter)),1,0)
A13: Shikara | B13: A couple must strive to remain resilient after regional hostilities drive them from their beloved home into a refugee camp. | C13: Romance | D13: =IFERROR(INDEX(tblNetflix[type],MATCH($A13,tblNetflix[title],0)),"") | E13: =IFERROR(INDEX(tblNetflix[rating],MATCH($A13,tblNetflix[title],0)),"") | F13: =IFERROR(INDEX(tblNetflix[year_added],MATCH($A13,tblNetflix[title],0)),"") | G13: =IF(AND(OR(YearFilter="All",$F13=YearFilter),OR(RatingFilter="All",$E13=RatingFilter),OR(TypeFilter="All",$D13=TypeFilter)),1,0)
... A21: Kyaa Kool Hain Hum 3 | B21: When an unlikely porn actor falls for a woman outside the industry, he employs his co-stars as a stand-in traditional family to impress her father. | C21: Family & Children | D21: =IFERROR(INDEX(tblNetflix[type],MATCH($A21,tblNetflix[title],0)),"") | E21: =IFERROR(INDEX(tblNetflix[rating],MATCH($A21,tblNetflix[title],0)),"") | F21: =IFERROR(INDEX(tblNetflix[year_added],MATCH($A21,tblNetflix[title],0)),"") | G21: =IF(AND(OR(YearFilter="All",$F21=YearFilter),OR(RatingFilter="All",$E21=RatingFilter),OR(TypeFilter="All",$D21=TypeFilter)),1,0)

Sheet Pivot_Tables
A1: Total Titles | F1: Genre Distribution (Top 12)
A2: Metric | B2: Count | F2: Genre | G2: Titles
A3: Total Indian Titles | B3: =ROWS(tblNetflix) | F3: International Movies | G3: =COUNTIF(tblGenre[Genre],F3)
F4: Dramas | G4: =COUNTIF(tblGenre[Genre],F4)
A5: Movies vs TV Shows | F5: Comedies | G5: =COUNTIF(tblGenre[Genre],F5)
A6: Type | B6: Count | F6: Independent Movies | G6: =COUNTIF(tblGenre[Genre],F6)
A7: Movie | B7: =COUNTIF(tblNetflix[type],"Movie") | F7: Action & Adventure | G7: =COUNTIF(tblGenre[Genre],F7)
A8: TV Show | B8: =COUNTIF(tblNetflix[type],"TV Show") | F8: Romantic Movies | G8: =COUNTIF(tblGenre[Genre],F8)
F9: Music & Musicals | G9: =COUNTIF(tblGenre[Genre],F9)
A10: Year-wise Content Added | F10: Thrillers | G10: =COUNTIF(tblGenre[Genre],F10)
A11: Year | B11: Titles Added | F11: International TV Shows | G11: =COUNTIF(tblGenre[Genre],F11)
A12: 2016 | B12: =COUNTIF(tblNetflix[year_added],A12) | F12: Horror Movies | G12: =COUNTIF(tblGenre[Genre],F12)
A13: 2017 | B13: =COUNTIF(tblNetflix[year_added],A13) | F13: TV Dramas | G13: =COUNTIF(tblGenre[Genre],F13)
A14: 2018 | B14: =COUNTIF(tblNetflix[year_added],A14) | F14: Documentaries | G14: =COUNTIF(tblGenre[Genre],F14)
A15: 2019 | B15: =COUNTIF(tblNetflix[year_added],A15)
A16: 2020 | B16: =COUNTIF(tblNetflix[year_added],A16) | F16: Rating Distribution
A17: 2021 | B17: =COUNTIF(tblNetflix[year_added],A17) | F17: Rating | G17: Titles
F18: TV-14 | G18: =COUNTIF(tblNetflix[rating],F18)
A19: Top 10 Directors | F19: TV-MA | G19: =COUNTIF(tblNetflix[rating],F19)
A20: Director | B20: Titles | F20: TV-PG | G20: =COUNTIF(tblNetflix[rating],F20)
A21: David Dhawan | B21: =COUNTIF(tblNetflix[director],A21) | F21: TV-Y7 | G21: =COUNTIF(tblNetflix[rating],F21)
A22: Ram Gopal Varma | B22: =COUNTIF(tblNetflix[director],A22) | F22: PG-13 | G22: =COUNTIF(tblNetflix[rating],F22)
A23: Ashutosh Gowariker | B23: =COUNTIF(tblNetflix[director],A23) | F23: TV-G | G23: =COUNTIF(tblNetflix[rating],F23)
A24: Rajkumar Santoshi | B24: =COUNTIF(tblNetflix[director],A24) | F24: PG | G24: =COUNTIF(tblNetflix[rating],F24)
A25: Imtiaz Ali | B25: =COUNTIF(tblNetflix[director],A25) | F25: NR | G25: =COUNTIF(tblNetflix[rating],F25)
A26: Anees Bazmee | B26: =COUNTIF(tblNetflix[director],A26) | F26: TV-Y | G26: =COUNTIF(tblNetflix[rating],F26)
A27: Sooraj R. Barjatya | B27: =COUNTIF(tblNetflix[director],A27) | F27: R | G27: =COUNTIF(tblNetflix[rating],F27)
A28: Milan Luthria | B28: =COUNTIF(tblNetflix[director],A28) | F28: TV-Y7-FV | G28: =COUNTIF(tblNetflix[rating],F28)
A29: Rohit Shetty | B29: =COUNTIF(tblNetflix[director],A29)
A30: Prakash Jha | B30: =COUNTIF(tblNetflix[director],A30) | F30: AI Theme Distribution (Top 20 sample)
F31: Theme | G31: Titles
F32: Crime & Thriller | G32: =COUNTIF(tblTheme[Theme],F32)
F33: Family & Children | G33: =COUNTIF(tblTheme[Theme],F33)
F34: Romance | G34: =COUNTIF(tblTheme[Theme],F34)
F35: Historical & Cultural | G35: =COUNTIF(tblTheme[Theme],F35)
F36: Education & Youth | G36: =COUNTIF(tblTheme[Theme],F36)
F37: Other | G37: =COUNTIF(tblTheme[Theme],F37)
F38: Comedy | G38: =COUNTIF(tblTheme[Theme],F38)
F39: Note: theme tagging covers a 20-title AI-categorized sample, not the full catalogue.

Sheet Chart_Source
A1: TYPE | B1: Count | D1: YEAR | E1: Count | G1: DIRECTOR (COMEDIES) | H1: COMEDY TITLE COUNT | J1: GENRE | K1: Count | M1: RATING | N1: Count | P1: THEME | Q1: Count | S1: YearList | T1: GenreList | U1: RatingList | V1: TypeList
A2: Movie | B2: =SUMIFS(tblNetflix[IncludeRow],tblNetflix[type],A2) | D2: 2016 | E2: =SUMIFS(tblNetflix[IncludeRow],tblNetflix[year_added],D2) | G2: =LET(d,tblNetflix[director],inc,tblNetflix[IncludeRow],valid,(d<>"")*(inc=1),dirs,FILTER(d,valid,""),u,UNIQUE(dirs),c,MAP(u,LAMBDA(x,SUMIFS(tblNetflix[IncludeRow],tblNetflix[director],x))),data,FILTER(HSTACK(u,c),u<>""),TAKE(SORTBY(data,CHOOSECOLS(data,2),-1,CHOOSECOLS(data,1),1),10)) | J2: International Movies | K2: =SUMIFS(tblGenre[IncludeRow_NoGenre],tblGenre[Genre],J2) | M2: TV-14 | N2: =SUMIFS(tblNetflix[IncludeRow],tblNetflix[rating],M2) | P2: Crime & Thriller | Q2: =SUMIFS(tblTheme[IncludeRow],tblTheme[Theme],P2) | S2: All | T2: All | U2: All | V2: All
A3: TV Show | B3: =SUMIFS(tblNetflix[IncludeRow],tblNetflix[type],A3) | D3: 2017 | E3: =SUMIFS(tblNetflix[IncludeRow],tblNetflix[year_added],D3) | J3: Dramas | K3: =SUMIFS(tblGenre[IncludeRow_NoGenre],tblGenre[Genre],J3) | M3: TV-MA | N3: =SUMIFS(tblNetflix[IncludeRow],tblNetflix[rating],M3) | P3: Family & Children | Q3: =SUMIFS(tblTheme[IncludeRow],tblTheme[Theme],P3) | S3: 2016 | T3: International Movies | U3: TV-14 | V3: Movie
D4: 2018 | E4: =SUMIFS(tblNetflix[IncludeRow],tblNetflix[year_added],D4) | J4: Comedies | K4: =SUMIFS(tblGenre[IncludeRow_NoGenre],tblGenre[Genre],J4) | M4: TV-PG | N4: =SUMIFS(tblNetflix[IncludeRow],tblNetflix[rating],M4) | P4: Romance | Q4: =SUMIFS(tblTheme[IncludeRow],tblTheme[Theme],P4) | S4: 2017 | T4: Dramas | U4: TV-MA | V4: TV Show
D5: 2019 | E5: =SUMIFS(tblNetflix[IncludeRow],tblNetflix[year_added],D5) | J5: Independent Movies | K5: =SUMIFS(tblGenre[IncludeRow_NoGenre],tblGenre[Genre],J5) | M5: TV-Y7 | N5: =SUMIFS(tblNetflix[IncludeRow],tblNetflix[rating],M5) | P5: Historical & Cultural | Q5: =SUMIFS(tblTheme[IncludeRow],tblTheme[Theme],P5) | S5: 2018 | T5: Comedies | U5: TV-PG
D6: 2020 | E6: =SUMIFS(tblNetflix[IncludeRow],tblNetflix[year_added],D6) | J6: Action & Adventure | K6: =SUMIFS(tblGenre[IncludeRow_NoGenre],tblGenre[Genre],J6) | M6: PG-13 | N6: =SUMIFS(tblNetflix[IncludeRow],tblNetflix[rating],M6) | P6: Education & Youth | Q6: =SUMIFS(tblTheme[IncludeRow],tblTheme[Theme],P6) | S6: 2019 | T6: Independent Movies | U6: TV-Y7
D7: 2021 | E7: =SUMIFS(tblNetflix[IncludeRow],tblNetflix[year_added],D7) | J7: Romantic Movies | K7: =SUMIFS(tblGenre[IncludeRow_NoGenre],tblGenre[Genre],J7) | M7: TV-G | N7: =SUMIFS(tblNetflix[IncludeRow],tblNetflix[rating],M7) | P7: Other | Q7: =SUMIFS(tblTheme[IncludeRow],tblTheme[Theme],P7) | S7: 2020 | T7: Action & Adventure | U7: PG-13
J8: Music & Musicals | K8: =SUMIFS(tblGenre[IncludeRow_NoGenre],tblGenre[Genre],J8) | M8: PG | N8: =SUMIFS(tblNetflix[IncludeRow],tblNetflix[rating],M8) | P8: Comedy | Q8: =SUMIFS(tblTheme[IncludeRow],tblTheme[Theme],P8) | S8: 2021 | T8: Romantic Movies | U8: TV-G
J9: Thrillers | K9: =SUMIFS(tblGenre[IncludeRow_NoGenre],tblGenre[Genre],J9) | M9: NR | N9: =SUMIFS(tblNetflix[IncludeRow],tblNetflix[rating],M9) | T9: Music & Musicals | U9: PG
J10: International TV Shows | K10: =SUMIFS(tblGenre[IncludeRow_NoGenre],tblGenre[Genre],J10) | M10: TV-Y | N10: =SUMIFS(tblNetflix[IncludeRow],tblNetflix[rating],M10) | T10: Thrillers | U10: NR
J11: Horror Movies | K11: =SUMIFS(tblGenre[IncludeRow_NoGenre],tblGenre[Genre],J11) | M11: R | N11: =SUMIFS(tblNetflix[IncludeRow],tblNetflix[rating],M11) | T11: International TV Shows | U11: TV-Y
J12: TV Dramas | K12: =SUMIFS(tblGenre[IncludeRow_NoGenre],tblGenre[Genre],J12) | M12: TV-Y7-FV | N12: =SUMIFS(tblNetflix[IncludeRow],tblNetflix[rating],M12) | T12: Horror Movies | U12: R
G13: Top 10 Directors update automatically from the selected Genre + Year + Rating + Type filters. | J13: Documentaries | K13: =SUMIFS(tblGenre[IncludeRow_NoGenre],tblGenre[Genre],J13) | T13: TV Dramas | U13: TV-Y7-FV
T14: Documentaries
T15: TV Comedies
T16: Children & Family Movies
T17: Sports Movies
T18: Romantic TV Shows
T19: Kids' TV
T20: Sci-Fi & Fantasy
T21: Classic Movies
T22: Docuseries
T23: Crime TV Shows
T24: TV Horror
T25: Reality TV
... T37: Teen TV Shows

Sheet Dashboard
A1: NETFLIX INDIA CONTENT DEEP DIVE
A4: Interactive Microsoft Excel Dashboard | G4: ="Prepared: "&TEXT(TODAY(),"dd-mmm-yyyy")&" | Prepared By: Data Analytics Team"
A6: FILTERS
A7: Year | B7: All | D7: Genre | E7: All | G7: Rating | H7: All | J7: Type | K7: All
D8: Genre selector controls Top 10 Directors
A9: 🎬 | E9: 🎥 | I9: 📺
A11: =SUM(tblNetflix[IncludeRow]) | E11: =Chart_Source!$B$2 | I11: =Chart_Source!$B$3
A14: TOTAL INDIAN TITLES | E14: MOVIES | I14: TV SHOWS
A16: 🏷️ | E16: 🎭 | I16: ⭐
A18: =INDEX(Chart_Source!$J$2:$J$13,MATCH(MAX(Chart_Source!$K$2:$K$13),Chart_Source!$K$2:$K$13,0)) | E18: =INDEX(Chart_Source!$G$2:$G$11,MATCH(MAX(Chart_Source!$H$2:$H$11),Chart_Source!$H$2:$H$11,0)) | I18: =INDEX(Chart_Source!$M$2:$M$12,MATCH(MAX(Chart_Source!$N$2:$N$12),Chart_Source!$N$2:$N$12,0))
A21: TOP GENRE | E21: TOP DIRECTOR | I21: MOST COMMON RATING
G38: Top 10 Directors (Selected Genre)
A74: KEY INSIGHTS | G74: BUSINESS RECOMMENDATIONS
A75: • Movies dominate Indian Netflix content, outnumbering TV Shows roughly 11 to 1 (962 vs 84 titles). | G75: • Increase investment in regional-language and non-Hindi Indian content to diversify beyond the current catalogue mix.
A76: • International Movies is the single largest genre tag (864 tag-instances), ahead of Dramas (662) and Comedies (323). | G76: • Expand high-performing genres such as International Movies, Dramas and Comedies, which already drive the bulk of engagement.
A77: • Indian content additions accelerated sharply after 2017 -- titles added jumped from 162 in 2017 to a peak of 349 in 2018. | G77: • Develop more family-oriented and youth/education-themed titles to balance the current Crime & Thriller-heavy content skew.
A78: • TV-14 is the most common content rating (572 titles, ~55% of the catalogue), followed by TV-MA (266). | G78: • Strengthen long-term partnerships with consistently prolific directors to secure a steady content pipeline.
A79: • A small group of veteran Bollywood directors -- led by David Dhawan (9 titles) -- account for a disproportionate share of repeat contributions. | G79: • Prioritize TV-14 and TV-MA rated content, which together cover over 80% of the current library and the broadest addressable audience.
A80: • AI theme tagging on a 20-title sample shows Crime & Thriller and Family & Children as the most recurring narrative themes. | G80: • Continue scaling year-on-year content additions, building on the growth trajectory established since 2017.
